Workbook

Sheet Geral
A1: Código | B1: Disciplina | C1: Conteudista | D1: DI | E1: Número de semanas | F1: Videoaulas | G1: Bim
A2: PJI610 | B2: Projeto Integrador em Computação VI | C2: Marcelo Garcia Manzato | D2: Alfredo | E2: 7 | F2: (1-7) | G2: 2024.1
A3: PJI420 | B3: Projeto Integrador I - Negócios e Produção | C3: Antonio Francisco Savi | D3: Alfredo | E3: 7 | F3: (1-7) | G3: 2024.1
A4: ADM310 | B4: Estratégia e Governança | C4: Bruna Liria Avelhan | D4: Fábio | E4: 8 | F4: (11-21) | G4: 2024.1
A5: DIR300 | B5: Noções básicas de direito público e privado | C5: Luciana Lopes Canavez | D5: Juliana | E5: 8 | F5: (11-21) | G5: 2024.1
A6: COM311 | B6: Desenho Técnico Assistido por Computador | C6: Antonio Francisco Savi | D6: Daniel | E6: 8 | F6: (11-21) | G6: 2024.1
A7: SDD001 | B7: Didática | C7: Simone Telles | D7: Claudia | E7: 8 | F7: (11-21) | G7: 2024.1
A8: SFH001 | B8: Fundamentos Históricos, Filosóficos e Sociológicos da Educação | C8: Eli Vagner Francisco Rodrigues | D8: Ieda | E8: 8 | F8: (11-21) | G8: 2024.1
A9: COM590 | B9: Compiladores | C9: Júlio Cezar Estrella | D9: Fábio | E9: 8 | F9: (11-21) | G9: 2024.2
A10: ADM330 | B10: Conceitos e práticas de marketing | C10: Renato da Costa dos Santos | D10: Fábia | E10: 8 | F10: (11-21) | G10: 2024.2
A11: ADM320 | B11: Gestão da Produção e Operações | C11: Renato da Costa dos Santos | D11: Mirtes | E11: 8 | F11: (11-21) | G11: 2024.2
A12: PES320 | B12: Controle Estatístico e Gestão da Qualidade | C12: Marco Aurélio Soares De Castro | D12: Rafael | E12: 8 | F12: (11-21) | G12: 2024.2
A13: SAA001 | B13: Avaliação Educacional e da Aprendizagem | C13: Eric Ferdinando Kanai Passone | D13: Renata | E13: 8 | F13: (11-21) | G13: 2024.2
... A24: PJI120 | B24: Projeto Integrador - Adaptação curricular | C24: Mônica | D24: Alfredo | E24: 7 | F24: (1-7) | G24: 2024.3
A25: MAT300 | B25: Fundamentos da Matemática Elementar | D25: Rafael | E25: 8 | F25: (11-21) | G25: 2024.3
A26: COM100 | B26: Pensamento Computacional | C26: Marcos Borges | G26: 2024.3
A27: ADM300 | B27: Legislação e Responsabilidade Profissional | C27: Juliana Novi | D27: Fábio | E27: 8 | F27: (11-21) | G27: 2024.4
A28: SEJ001 | B28: Educação de Jovens e Adultos | C28: Adriana Batista de Souza Koide | D28: Juliana | E28: 8 | F28: (11-21) | G28: 2024.4
A29: CIN300 | B29: Gestão de Sistemas de Informação | C29: Antonio Francisco Savi | D29: Daniel | E29: 8 | F29: (11-21) | G29: 2024.4
A30: ADM370 | B30: Marketing Digital | C30: Marina Toledo Lourenção Rocha | D30: Fábia | E30: 8 | F30: (11-21) | G30: 2024.4
A31: EPR310 | B31: Pesquisa Operacional II | C31: Anibal Tavares De Azevedo | D31: Ieda | E31: 8 | F31: (11-21) | G31: 2024.4
A32: ADM360 | B32: Análise e modelagem de processos | C32: Renato da Costa dos Santos | D32: Joel | E32: 8 | F32: (11-21) | G32: 2024.4
A33: HFE001 | B33: Filosofia da Educação | C33: Ronildo Alves Dos Santos | D33: autoinstrucional | E33: 8 | F33: (11-21) | G33: 2024.4
A34: HSE001 | B34: Sociologia da Educação | C34: Eli Vagner Francisco Rodrigues | D34: autoinstrucional | E34: 8 | F34: (11-21) | G34: 2024.4
A35: LET340 | B35: Gramática de Língua Portuguesa: morfologia | D35: Raquel/Cláudia | E35: 8 | F35: (11-21) | G35: 2024.4
A36: MAT310 | B36: Geometria Analítica | C36: Glauce Barbosa Verao | D36: Raquel | E36: 8 | F36: (11-21) | G36: 2024.4
A37: MMB002 | B37: Matemática básica | C37: Prof.Rúbia Barcelos Amaral | E37: 8 | F37: (11-21) | G37: 2024.2 AC
A38: FIS300 | B38: Física do Movimento (Engenharia de Computação 2020.1) | E38: 8 | F38: (11-21) | G38: 2024.2 AC
A39: EDU310 | B39: Letramento em LIBRAS para professores | C39: Karina Soledad Maldonado Molina | E39: 8 | F39: (11-21) | G39: 2024.3 AC
A40: SFI002 | B40: Fundamentos da Educação Infantil II | C40: Claudia Panizzolo | G40: 2024.3 AC
A41: TPL504 | B41: Projeto Integrador para Licenciatura IV | C41: Taitiâny Kárita Bonzanini | G41: 2024.3 AC
A42: LET320 | B42: Literatura e Cultura Brasileira | C42: Marise Soares Hansen | E42: 8 | F42: (11-21) | G42: 2024.3 AC
A43: LIN310 | B43: Aquisição da Linguagem: Oralidade e Escrita | C43: Lúcia Regiane Lopes-Damasio | E43: 8 | F43: (11-21) | G43: 2024.3 AC
A44: COM390 | B44: Engenharia de Software | G44: 2024.3 AC
A45: PJI240 | B45: Projeto Integrador em Computação II | G45: 2024.3 AC
A46: LET110 | B46: Leitura e Produção de textos | C46: Vanessa Martins do Monte | G46: 2024.3 AC
A47: SOC100 | B47: Ética, cidadania e Sociedade | C47: Eli Vagner Francisco Rodrigues | G47: 2024.3 AC
A48: EDU320 | B48: Educação Mediada por Tecnologias | C48: Raquel Rosan Christino Gitahy | E48: 8 | F48: (11-21) | G48: 2024.4 AC
A49: SMA001 | B49: Metodologias Ativas de Aprendizagem: Projetos Interdisciplinares | C49: Adriana Bauer | E49: 8 | F49: (11-21) | G49: 2024.4 AC
A50: LET330 | B50: Gramática de Língua Portuguesa II | C50: Lúcia Regiane Lopes-Damasio | E50: 8 | F50: (11-21) | G50: 2024.4 AC
A51: INT100 | B51: Projetos e Métodos para a Produção do Conhecimento | C51: Darlene Ferreira | G51: 2024.4 AC
A52: LET100 | B52: Inglês | C52: Cristina Mayer Acunzo | G52: 2024.4 AC

Sheet 2024.1
A1: CÓD | B1: Disciplina | C1: Semanas | D1: Nº de aulas | E1: Título da aula | F1: Sinopse da Videoaula | G1: Link no YouTube | H1: Slide na pasta | I1: Status | J1: Download | K1: ID (TV Cultura) | L1: Duração | M1: Professor | N1: DI
A2: PJI610 | B2: Projeto Integrador em Computação VI | C2: Quinzena 1 | D2: AULA 01 | E2: Apresentação | G2: https://youtu.be/ZNFk0kUyd3w | H2: ok | I2: finalizado | J2: ok | K2: 2390P013365 | L2: 0.010497685 | M2: =VLOOKUP(A2,Geral!$A$1:$D$36,3,FALSE) -> Marcelo Garcia Manzato
D3: AULA 02 | E3: Plano de Negócios | G3: https://youtu.be/8puMOD6z8sc | H3: ok | I3: finalizado | J3: ok | K3: 2390P013366 | L3: 0.011759259
C4: Quinzena 3 | D4: AULA 03 | E4: Desenvolvimento Mobile | G4: https://youtu.be/J7I7vDCjVWM | H4: ok | I4: finalizado | J4: ok | K4: 2390P013367 | L4: 0.014050926
D5: AULA 04 | E5: Processamento digital de sinais | G5: https://youtu.be/K9v1J8KY760 | H5: ok | I5: finalizado | J5: ok | K5: 2390P013368 | L5: 0.013506944
C6: Quinzena 4 | D6: AULA 05 | E6: Internet das Coisas | G6: https://youtu.be/YRoWxDfcLXU | H6: ok | I6: finalizado | J6: ok | K6: 2390P013369 | L6: 0.011851852
D7: AULA 06 | E7: Sistemas Embarcados | G7: https://youtu.be/aKfI06JSc0M | H7: ok | I7: finalizado | J7: ok | K7: 2390P013370 | L7: 0.012141204
C8: Quinzena 6 | D8: AULA 07 | E8: Interface com usuário | G8: https://youtu.be/Ws3QP7nEfeI | H8: ok | I8: finalizado | J8: ok | K8: 2390P013371 | L8: 0.013993056
A10: PJI420 | B10: Projeto Integrador I - Negócios e Produção | C10: Quinzena 1 | D10: AULA 0 | E10: Apresentação | G10: https://youtu.be/9hYte8fBE8M | H10: ok | I10: finalizado | J10: ok | K10: 2390P013597 | L10: 0.0018518519
D11: AULA 01 | E11: Resumo geral do Projeto Integrador | G11: https://youtu.be/IH6uEr7bLcM | H11: ok | I11: finalizado | J11: ok | K11: 2390P013372 | L11: 0.012326389 | M11: =VLOOKUP(A10,Geral!$A$1:$D$36,3,FALSE) -> Antonio Francisco Savi
C12: Quinzena 2 | D12: AULA 02 | E12: Aproximação ao tema, escolha do local e observação in loco | G12: https://youtu.be/exBooQA-9_k | H12: ok | I12: finalizado | J12: ok | K12: 2390P013373 | L12: 0.0092361111
C13: Quinzena 3 | D13: AULA 03 | E13: Definição e estudo sobre o tema | G13: https://youtu.be/UD4mOD6V0Ys | H13: ok | I13: finalizado | J13: ok | K13: 2390P013374 | L13: 0.011759259
C14: Quinzena 4 | D14: AULA 04 | E14: Framework de processo e sistematização do projeto | G14: https://youtu.be/FvYKUueEtcY | H14: ok | I14: finalizado | J14: ok | K14: 2390P013375 | L14: 0.0094560185
C15: Quinzena 5 | D15: AULA 05 | E15: Gestão de projetos | G15: https://youtu.be/ohcPzmZ5gEI | H15: ok | I15: finalizado | J15: ok | K15: 2390P013376 | L15: 0.0095717593
C16: Quinzena 6 | D16: AULA 06 | E16: Ferramentas e métodos para confecção do protótipo | G16: https://youtu.be/c3yJPsBslwY | H16: ok | I16: finalizado | J16: ok | K16: 2390P013377 | L16: 0.0088888889
C17: Quinzena 7 | D17: AULA 07 | E17: Melhoria da solução | G17: https://youtu.be/R6babxG24H8 | H17: ok | I17: finalizado | J17: ok | K17: 2390P013378 | L17: 0.0088773148
A19: ADM310 | B19: Estratégia e Governança | C19: Semana 1 | D19: AULA 01 | E19: Estratégia empresarial: princípios e enfoques | G19: https://youtu.be/L2JM0shM98A | H19: OK | I19: finalizado | J19: ok | K19: 2390P013484 | L19: 0.013645833 | M19: =VLOOKUP(A19,Geral!$A$1:$D$36,3,FALSE) -> Bruna Liria Avelhan
D20: AULA 02 | E20: O modelo das 5 forças de Porter aplicado à Tecnologia da Informação | G20: https://youtu.be/VPsducNxa2U | H20: OK | I20: finalizado | J20: ok | K20: 2390P013485 | L20: 0.012673611
D21: AULA 03 | E21: Governança corporativa e governança de TI | G21: https://youtu.be/zLkn7c7PZpE | H21: OK | I21: finalizado | J21: ok | K21: 2390P013486 | L21: 0.014594907
C22: Semana 2 | D22: AULA 04 | E22: Planejamento estratégico da TI | G22: https://youtu.be/I6L_3W8HDq8 | H22: OK | I22: finalizado | J22: ok | K22: 2390P013487 | L22: 0.014097222
D23: AULA 05 | E23: Subsistemas de TI: objetivos e direcionamento | G23: https://youtu.be/54Ou0HYm2aw | H23: OK | I23: finalizado | J23: ok | K23: 2390P013488 | L23: 0.014016204
D24: AULA 06 | E24: Subsistemas de TI: Desenvolvimento e entrega | G24: https://youtu.be/pjHVT_frFis | H24: OK | I24: finalizado | J24: ok | K24: 2390P013489 | L24: 0.014108796
C25: Semana 3 | D25: AULA 07 | E25: Cobit: Introtução e Princípios-chaves | G25: https://youtu.be/-2qVeLe47mg | H25: OK | I25: finalizado | J25: ok | K25: 2390P013490 | L25: 0.015115741
D26: AULA 08 | E26: Cobit: Processos de TI e diretrizes de implantação | G26: https://youtu.be/xPDHyVqYjM8 | H26: OK | I26: finalizado | J26: ok | K26: 2390P013491 | L26: 0.015289352
D27: AULA 09 | E27: ITIL: Estratégia de Serviço | G27: https://youtu.be/0E2oP7PNRsg | H27: OK | I27: finalizado | J27: ok | K27: 2390P013492 | L27: 0.013726852
C28: Semana 4 | D28: AULA 10 | E28: ITIL: Desenho do serviço | G28: https://youtu.be/VIyr-n-YuuM | H28: OK | I28: finalizado | J28: ok | K28: 2390P013493 | L28: 0.014560185
D29: AULA 11 | E29: ITIL: Transição de serviço | G29: https://youtu.be/b7pVctSbCeA | H29: OK | I29: finalizado | J29: ok | K29: 2390P013494 | L29: 0.012777778
D30: AULA 12 | E30: ITIL: Operação de serviço e melhoria contínua de serviço | G30: https://youtu.be/dcQfk3oRYW8 | H30: OK | I30: finalizado | J30: ok | K30: 2390P013495 | L30: 0.01587963
C31: Semana 5 | D31: AULA 13 | E31: Governança de dados: as leis de proteção de dados | F31: Com chroma | G31: https://youtu.be/NsXKKE1E9Tw | H31: OK | I31: finalizado | J31: ok | K31: 2390P013496 | L31: 0.015902778
D32: AULA 14 | E32: Governança de dados: a ética nos dados | G32: https://youtu.be/Ah0prt98pSY | H32: OK | I32: finalizado | J32: ok | K32: 2390P013497 | L32: 0.014756944
D33: AULA 15 | E33: Governança de dados: metadados | F33: Com chroma | G33: https://youtu.be/aZLOEscPZCU | H33: OK | I33: finalizado | J33: ok | K33: 2390P013498 | L33: 0.013981481
C34: Semana 6 | D34: AULA 16 | E34: Arquitetura Corporativa | G34: https://youtu.be/v3arSFbHjLI | H34: OK | I34: finalizado | J34: ok | K34: 2390P013499 | L34: 0.012233796
B36: Noções básicas de direito público e privado | C36: Semana 1 | D36: AULA 0 | E36: Apresentação | G36: https://youtu.be/wtpp-lhPYu8 | H36: ok | I36: finalizado | J36: ok | K36: 2390P013670 | L36: 0.0018171296 | M36: Luciana Canavez
D37: AULA 01 | E37: Direito constitucional e administrativo | F37: Nesta videoaula, você conhecerá e compreenderá quais são as instituições e como é a estrutura do Estado, seus princípios constitucionais e as garantias fundamentais. | G37: https://youtu.be/8CgErP60jdQ | H37: ok | I37: finalizado | J37: ok | K37: 2390P013532 | L37: 0.015729167
D38: AULA 02 | E38: Noções de Direito Administrativo | F38: Nesta videoaula, você conhecerá e compreenderá os princípios e fundamentos da administração pública. | G38: https://youtu.be/n-Had_bjEJ0 | H38: ok | I38: finalizado | J38: ok | K38: 2390P013533 | L38: 0.023969907
C39: Semana 2 | D39: AULA 03 | E39: Das pessoas naturais e jurídicas | F39: Nesta videoaula, a Profª Luciana Lopes Canavez abordará todas as normas referentes às pessoas naturais, tratando de temas como capacidade e incapacidade, e os direitos da personalidade. Estudaremos ainda quem são as pessoas jurídicas de direito público e privado. | G39: https://youtu.be/sKvhRsGFnGU | H39: ok | I39: finalizado | J39: ok | K39: 2390P013534 | L39: 0.017106481
D40: AULA 04 | E40: Do negócio jurídico, das obrigações contratos e responsabilidade civil | F40: Nesta videoaula, analisaremos os requisitos para estabelecer negócios jurídicos, a forma como se estabelecem os vínculos obrigacionais e contratuais, por exemplo o contrato de compra e venda, e as responsabilidades decorrentes desses vínculos (contratual e extracontratual). | G40: https://youtu.be/LnqwJRGveEM | H40: ok | I40: finalizado | J40: ok | K40: 2390P013535 | L40: 0.017731481
D41: AULA 05 | E41: Do direito de propriedade e da posse | F41: Nesta videoaula, estudaremos os direitos de posse e de propriedade e as formas de manutenção e conservação desses direitos. | G41: https://youtu.be/cMdulMVLSo0 | H41: ok | I41: finalizado | J41: ok | K41: 2390P013918 | L41: 0.014699074
C42: Semana 3 | D42: AULA 06 | E42: Noções gerais de Direito Empresarial | F42: Nesta videoaula, a Profª Luciana Lopes Canavez abordará todos os conceitos iniciais do Direito Empresarial, tratará da capacidade de ser empresário, das responsabilidades e da perda da capacidade de empresário. | G42: https://youtu.be/wAqjZMY82zQ | H42: ok | I42: finalizado | J42: ok | K42: 2390P013537 | L42: 0.014560185
A43: DIR300 | D43: AULA 07 | E43: Das Sociedades | F43: Nesta videoaula, analisaremos as sociedades personificadas e não personificadas, e trataremos dos tipos societários mais comuns, como a sociedade limitada, sociedade anônima e sociedade simples. | G43: https://youtu.be/RVWsz8pCPp0 | H43: ok | I43: finalizado | J43: ok | K43: 2390P013538 | L43: 0.01681713
C44: Semana 4 | D44: AULA 08 | E44: Introdução ao Direito Ambiental | F44: Nesta videoaula, a Profª Luciana Lopes Canavez abordará conceitos, normas e princípios do Direito Ambiental no Brasil, destacando a importância de sua preservação, inclusive para o universo das empresas. | G44: https://youtu.be/uum5GiavGB0 | H44: ok | I44: finalizado | J44: ok | K44: 2390P013539 | L44: 0.013159722
D45: AULA 09 | E45: Crimes Ambientais: Prevencão e reparação | F45: Nesta videoaula, analisaremos os crimes ambientais, as formas de prevenção e reparação, passando pela apuração das responsabilidades dos causadores de danos ao meio ambiente. | G45: https://youtu.be/R0L4EG-hVd8 | H45: ok | I45: finalizado | J45: ok | K45: 2390P013540 | L45: 0.015023148
C46: Semana 5 | D46: AULA 10 | E46: Sistema Tributário Nacional | F46: Nesta videoaula, a Profª Luciana Lopes Canavez abordará as normas referentes ao sistema tributário nacional, tratando de temas como os princípios gerais e as limitações ao poder de tributar. | G46: https://youtu.be/tzFL16-Kqdw | H46: ok | I46: finalizado | J46: ok | K46: 2390P013986 | L46: 0.016631944
D47: AULA 11 | E47: Tributos e obrigações fiscais das empresas | F47: Nesta videoaula, analisaremos os tributos federais, estaduais e municipais, e estudaremos as obrigações fiscais impostas às empresas. | G47: https://youtu.be/Xg_XgQXeGX8 | H47: ok | I47: finalizado | J47: ok | K47: 2390P013987 | L47: 0.015104167
C48: Semana 6 | D48: AULA 12 | E48: LGPD: Proteção de dados pessoais e da personalidade na internet | F48: Nesta videoaula, a Profª Luciana Lopes Canavez abordará as normas que regulamentam o uso da internet no Brasil e a proteção de dados pessoais na internet. | G48: https://youtu.be/PwDHciLZqLg | H48: ok | I48: finalizado | J48: ok | K48: 2390P013543 | L48: 0.015231481
D49: AULA 13 | E49: Relação de consumo no ambiente digital e responsabilidade civil por danos causados no ambiente digital | F49: Nesta videoaula, analisaremos as relações de consumo no ambiente digital e as normas aplicáveis à reparação de danos causados nessas relações. | G49: https://youtu.be/cU0ialCUYcg | H49: ok | I49: finalizado | J49: ok | K49: 2390P013544 | L49: 0.012314815
C50: Semana 7 | D50: AULA 14 | E50: Propriedade Intelectual e os principais institutos para o universo das empresas I | F50: Nesta videoaula, a Profª Luciana Lopes Canavez abordará o regramento sobre direitos autorais e conexos e a proteção dos programas de computador. | G50: https://youtu.be/BrLovMawC-0 | H50: ok | I50: finalizado | J50: ok | K50: 2390P013545 | L50: 0.014884259
D51: AULA 15 | E51: Propriedade Intelectual e os principais institutos para o universo das empresas II | F51: Nesta videoaula, analisaremos os direitos da propriedade industrial mais comumente usados pelas empresas, como a proteção das patentes, das marcas e dos desenhos industriais. | G51: https://youtu.be/vcIuR5N5iZQ | H51: ok | I51: finalizado | J51: ok | K51: 2390P014607 | L51: 0.014618056
A53: COM311 | B53: Desenho Técnico Assistido por Computador | C53: Semana 1 | D53: AULA 0 | E53: Apresentação | G53: https://youtu.be/A5cxGChQ9Ps | H53: ok | I53: finalizado | J53: ok | K53: 2390P015553 | L53: 0.0033680556 | M53: =VLOOKUP(A53,Geral!$A$1:$D$36,3,FALSE) -> Antonio Francisco Savi
D54: AULA 01 | E54: Introdução ao desenho técnico e sua importância na engenharia | G54: https://youtu.be/dAF356fZB8Y | H54: ok | I54: finalizado | J54: ok | K54: 2390P015554 | L54: 0.015439815
D55: AULA 02 | E55: Compreensão das normas e convenções de desenho técnico | G55: https://youtu.be/tfnsNfc6JA4 | H55: ok | I55: finalizado | J55: ok | K55: 2390P015555 | L55: 0.0094444444
D56: AULA 03 | E56: Familiarização com os instrumentos de desenho e sua utilização | G56: https://youtu.be/G0rCcaQw7ns | H56: ok | I56: finalizado | J56: ok | K56: 2390P015556 | L56: 0.0091319444
C57: Semana 2 | D57: AULA 04 | E57: Conceito de projeções ortogonais e sua relação com as vistas ortográficas. | G57: https://youtu.be/Xume9njgXU4 | H57: ok | I57: finalizado | J57: ok | K57: 2390P015557 | L57: 0.015347222
D58: AULA 05 | E58: Prática na criação de vistas ortográficas a partir de modelos tridimensionais. | G58: https://youtu.be/U8Liw6ckR28 | H58: ok | I58: finalizado | J58: ok | K58: 2390P015558 | L58: 0.0089467593
D59: AULA 06 | E59: Demonstração de exercícios de representação de objetos em diferentes vistas ortográficas | G59: https://youtu.be/E05nl_5Z9Ls | H59: ok | I59: finalizado | J59: ok | K59: 2390P015559 | L59: 0.010659722
C60: Semana 3 | D60: AULA 07 | E60: Utilização de vistas auxiliares para representar detalhes específicos de um objeto. | G60: https://youtu.be/uTT7Hj0VM7Y | H60: ok | I60: finalizado | J60: ok | K60: 2390P015560 | L60: 0.012662037
D61: AULA 08 | E61: Técnicas de criação de cortes em desenhos técnicos para visualizar características internas. | G61: https://youtu.be/Z3zhtX8FCxg | H61: ok | I61: finalizado | J61: ok | K61: 2390P015561 | L61: 0.011053241
D62: AULA 09 | E62: Exercícios práticos de criação de vistas auxiliares e cortes em diferentes objetos. | G62: https://youtu.be/D1Ov8IybffM | H62: ok | I62: finalizado | J62: ok | K62: 2390P015562 | L62: 0.0088310185
C63: Semana 4 | D63: AULA 10 | E63: Conceitos de cotagem e sua importância na interpretação de desenhos técnicos. | G63: https://youtu.be/jKzNkLfjBXM | H63: ok | I63: finalizado | J63: ok | K63: 2390P015563 | L63: 0.0087268519
D64: AULA 11 | E64: Normas e convenções para indicar dimensões e tolerâncias. | G64: https://youtu.be/uChC4A2HX9A | H64: ok | I64: finalizado | J64: ok | K64: 2390P015564 | L64: 0.011296296
D65: AULA 12 | E65: Prática na correta cotagem de desenhos técnicos, incluindo a indicação de tolerâncias. | G65: https://youtu.be/sxbnUPycGTk | H65: ok | I65: finalizado | J65: ok | K65: 2390P015565 | L65: 0.0087384259
C66: Semana 5 | D66: AULA 13 | E66: Técnicas de criação e interpretação de vistas em corte. | G66: https://youtu.be/NLdTdHtvveQ | H66: ok | I66: finalizado | J66: ok | K66: 2390P015566 | L66: 0.0081481481
D67: AULA 14 | E67: Aplicação das vistas em corte para representar seções transversais de objetos. | G67: https://youtu.be/uBDtWlEegZk | H67: ok | I67: finalizado | J67: ok | K67: 2390P015567 | L67: 0.0081712963
D68: AULA 15 | E68: Demonstração de exercícios de desenho de vistas em corte em diferentes objetos e configurações. | G68: https://youtu.be/3UdqEhPeLCw | H68: ok | I68: finalizado | J68: ok | K68: 2390P015568 | L68: 0.0085069444
C69: Semana 6 | D69: AULA 16 | E69: Introdução ao desenho isométrico e sua aplicação na representação de objetos tridimensionais | F69: Com chroma | G69: https://youtu.be/BMUrPf2rztw | H69: ok | I69: finalizado | J69: ok | K69: 2390P015569 | L69: 0.0069097222
D70: AULA 17 | E70: Técnicas de criação de desenhos isométricos | G70: https://youtu.be/WIFGPc9tYRM | H70: ok | I70: finalizado | J70: ok | K70: 2390P015570 | L70: 0.0075231481
D71: AULA 18 | E71: Prática na representação de objetos em desenhos isométricos | G71: https://youtu.be/DK3TRvAIG2o | H71: ok | I71: finalizado | J71: ok | K71: 2390P015571 | L71: 0.0065162037
C72: Semana 7 | D72: AULA 19 | E72: Conceitos básicos de desenho assistido por computador (CAD). | G72: https://youtu.be/-72Jch3RY-k | H72: ok | I72: finalizado | J72: ok | K72: 2390P015572 | L72: 0.010625
D73: AULA 20 | E73: Familiarização com o software CAD utilizado. | G73: https://youtu.be/Eg90mJ6A1oM | H73: ok | I73: finalizado | J73: ok | K73: 2390P015573 | L73: 0.014212963
A75: SDD001 | B75: Didática | C75: COSTURANDO | D75: COST. 01 | E75: Semana 01 | G75: https://youtu.be/GMGRBF5IWH8 | I75: finalizado | J75: ok | K75: 2390P013693 | L75: 0.0016319444 | M75: =VLOOKUP(A75,Geral!$A$1:$D$36,3,FALSE) -> Simone Telles
D76: COST. 02 | E76: Semana 02 | G76: https://youtu.be/of9oL7zntG0 | I76: finalizado | J76: ok | K76: 2390P013626 | L76: 0.0013657407
D77: COST. 03 | E77: Semana 03 | G77: https://youtu.be/nKvxLQWAhXA | I77: finalizado | J77: ok | K77: 2390P013627 | L77: 0.0015625
D78: COST. 04 | E78: Semana 04 | G78: https://youtu.be/IEJo416ylWQ | I78: finalizado | J78: ok | K78: 2390P013628 | L78: 0.001412037
D79: COST. 05 | E79: Semana 05 | G79: https://youtu.be/W7dPKUOejaQ | I79: finalizado | J79: ok | K79: 2390P013629 | L79: 0.0015856481
D80: COST. 06 | E80: Semana 06 | G80: https://youtu.be/ZoQKsuYTN7M | I80: finalizado | J80: ok | K80: 2390P013630 | L80: 0.0013425926
D81: COST. 07 | E81: Semana 07 | G81: https://youtu.be/PrZ0K2xnUKk | I81: finalizado | J81: ok | K81: 2390P013631 | L81: 0.0013888889
C82: Semana 1 | E82: Apresentação | G82: https://youtu.be/jKm0CQ_wzxU | I82: finalizado | J82: ok | K82: 2390P013632 | L82: 0.00072916667
E83: Dimensão Humana: Foco Socioemocional - Envolvimento escola / pais | G83: https://youtu.be/IdKEVuYDxn4 | I83: finalizado | J83: ok | K83: 2390P013633 | L83: 0.0038425926
E84: Dimensão Humana: Foco Socioemocional - Ensinar o aluno da melhor maneira | G84: https://youtu.be/eM32H79aigQ | I84: finalizado | J84: ok | K84: 2390P013634 | L84: 0.0019097222
E85: Dimensão Técnica: Foco didática - Estratégias pedagógicas na didática | G85: https://youtu.be/GDfgJ67qXhE | I85: finalizado | J85: ok | K85: 2390P013635 | L85: 0.0044444444
E86: Dimensão Técnica: O que é Didática? | G86: https://youtu.be/_spz1II91Y4 | I86: finalizado | J86: ok | K86: 2390P013636 | L86: 0.0034722222
E87: Dimensão Política: Foco no Planejamento | G87: https://youtu.be/ytYmO5rSwOk | I87: finalizado | J87: ok | K87: 2390P013637 | L87: 0.0032407407
E88: Dimensão Técnica: Foco na avaliação da aprendizagem | G88: https://youtu.be/XYcvXdhetRQ | I88: finalizado | J88: ok | K88: 2390P013638 | L88: 0.0038078704
C89: Semana 2 | E89: Tour pela escola | G89: https://youtu.be/sGKlKdJGHfg | I89: finalizado | J89: ok | K89: 2390P013640 | L89: 0.0011111111
E90: Os documentos curriculares: Currículo Paulista e Projeto Político Pedagógico | G90: https://youtu.be/a6HhKNNGR64 | I90: finalizado | J90: ok | K90: 2390P013641 | L90: 0.0049884259
C91: Semana 3 | E91: A BNCC e o planejamento semanal | G91: https://youtu.be/MCT5AsOeJhQ | I91: finalizado | J91: ok | K91: 2390P013643 | L91: 0.0059606481
E92: A construção de competência e as metodologias ativas | G92: https://youtu.be/INFvX2AiYFM | I92: finalizado | J92: ok | K92: 2390P013644 | L92: 0.0019675926
C93: Semana 4 | E93: Desvendando a BNCC da Computação e o Pensamento Computacional | G93: https://youtu.be/NexqKaLns8g | I93: finalizado | J93: ok | K93: 2390P013646 | L93: 0.01568287
E94: Os pilares do Pensamento computacional na prática | G94: https://youtu.be/wP6zl1ymASw | I94: finalizado | J94: ok | K94: 2390P013639 | L94: 0.016006944
E95: Pensamento Computacional na sala de aula | G95: https://youtu.be/aJPStO1yRCI | I95: finalizado | J95: ok | K95: 2390P013642 | L95: 0.0099652778
C96: Semana 5 | E96: Estratégia de Planejamento Curricular: Uma Visão Experiente | G96: https://youtu.be/bb5cphNGQK8 | I96: finalizado | J96: ok | K96: 2390P013645 | L96: 0.01275463
E97: Práticas Pedagógicas em Ação: Da Teoria á Sala de Aula | G97: https://youtu.be/7bGuKtAIUO0 | I97: finalizado | J97: ok | K97: 2390P014154 | L97: 0.010416667
C98: Semana 6 | E98: Construindo Aulas: Do Planejamento à Prática | G98: https://youtu.be/sgPBkfAWWNI | I98: finalizado | J98: ok | K98: 2390P014263 | L98: 0.014583333
E99: Criatividade em Ação: Inspirados pelos Alunos | G99: https://youtu.be/nSWovJaxA84 | I99: finalizado | J99: ok | K99: 2390P014264 | L99: 0.0069328704
E100: Didática sob o Olhar dos Alunos | G100: https://youtu.be/wzXQtfKq-sc | I100: finalizado | J100: ok | K100: 2390P014265 | L100: 0.0097222222
C101: Semana 7 | E101: Perspectiva em avaliação: discutindo sobre Práticas Eficientes | G101: https://youtu.be/K3K4r1CBrm8 | I101: finalizado | K101: 2390P014338 | L101: 0.017546296
E102: Avaliação além das notas: experiência da escola Angelo Bizzo | G102: https://youtu.be/otoZBLn168c | I102: finalizado | K102: 2390P014339 | L102: 0.0072685185
A104: SFH001 | B104: Fundamentos Históricos, Filosóficos e Sociológicos da Educação | C104: Semana 1 | D104: AULA 01 | E104: Introdução: As relações entre filosofia, sociologia e educação | G104: https://youtu.be/qpr74JGSupc | H104: ok | I104: finalizado | J104: ok | K104: 2390P013554 | L104: 0.012418981 | M104: =VLOOKUP(A104,Geral!$A$1:$D$36,3,FALSE) -> Eli Vagner Francisco Rodrigues
D105: AULA 02 | E105: Introdução: As relações entre filosofia, sociologia e educação part.2 | G105: https://youtu.be/ip7C-LPy2Kg | H105: ok | I105: finalizado | J105: ok | K105: 2390P013555 | L105: 0.012361111
C106: Semana 2 | D106: AULA 03 | E106: A educação no período Colonial | G106: https://youtu.be/zYYpFHj2GoM | H106: ok | I106: finalizado | J106: ok | K106: 2390P013556 | L106: 0.013113426
...

Sheet 2024.2
A1: CÓD | B1: Disciplina | C1: Semanas | D1: Nº de aulas | E1: Título da aula | F1: Sinopse da Videoaula | G1: Link no YouTube | H1: Slide na pasta | I1: Status | J1: Download | K1: ID (TV Cultura) | L1: Duração | M1: Professor | N1: DI
A2: COM590 | B2: Compiladores | C2: Semana 1 | D2: AULA 0 | E2: Apresentação | G2: https://youtu.be/4_7ttKOawbY | H2: OK | I2: finalizado | J2: ok | K2: 2390P013671 | L2: 0.0034606481 | M2: =VLOOKUP(A2,Geral!$A$1:$D$36,3,FALSE) -> Júlio Cezar Estrella
D3: AULA 01 | E3: Introdução aos Compiladores - Parte 1 | G3: https://youtu.be/IO8L7ZcGIBE | H3: OK | I3: finalizado | J3: ok | K3: 2390P013672 | L3: 0.013726852
D4: AULA 02 | E4: Introdução aos Compiladores - Parte 2 | G4: https://youtu.be/-fUIAZslUec | H4: OK | I4: finalizado | J4: ok | K4: 2390P013673 | L4: 0.011805556
D5: AULA 03 | E5: Introdução aos Compiladores - Parte 3 | G5: https://youtu.be/jcsNH9g1eWY | H5: OK | I5: finalizado | J5: ok | K5: 2390P013674 | L5: 0.01525463
C6: Semana 2 | D6: AULA 04 | E6: Análise Léxica - Parte 1 | G6: https://youtu.be/7Il_3wWc1Ic | H6: OK | I6: finalizado | J6: ok | K6: 2390P013675 | L6: 0.011041667
D7: AULA 05 | E7: Análise Léxica - Parte 2 | G7: https://youtu.be/mSGgoxHj834 | H7: OK | I7: finalizado | J7: ok | K7: 2390P013676 | L7: 0.014456019
D8: AULA 06 | E8: Análise Sintática - Parte 1 | G8: https://youtu.be/-VNmgcnsseo | H8: OK | I8: finalizado | J8: ok | K8: 2390P013677 | L8: 0.010069444
C9: Semana 3 | D9: AULA 07 | E9: Análise Sintática - Parte 2 | G9: https://youtu.be/F3V7q1L-_WM | H9: OK | I9: finalizado | J9: ok | K9: 2390P013678 | L9: 0.011053241
D10: AULA 08 | E10: Gramáticas | G10: https://youtu.be/DSgAHKDxHt4 | H10: OK | I10: finalizado | J10: ok | K10: 2390P013679 | L10: 0.0128125
D11: AULA 09 | E11: Árvore de Derivação | G11: https://youtu.be/mvTLPr_yi9Q | H11: OK | I11: finalizado | J11: ok | K11: 2390P013680 | L11: 0.011469907
C12: Semana 4 | D12: AULA 10 | E12: Tipos de Análise e Algoritmos | G12: https://youtu.be/m_oCazmF9i8 | H12: OK | I12: finalizado | J12: ok | K12: 2390P013681 | L12: 0.00875
D13: AULA 11 | E13: Análise Sintática Descendente | G13: https://youtu.be/jdbqaNVLRU8 | H13: OK | I13: finalizado | J13: ok | K13: 2390P013682 | L13: 0.01193287
D14: AULA 12 | E14: Análise Sintática Ascendente | G14: https://youtu.be/1NcdHjsnyaM | H14: OK | I14: finalizado | J14: ok | K14: 2390P013683 | L14: 0.009537037
C15: Semana 5 | D15: AULA 13 | E15: Análise Semântica - Parte 1 | G15: https://youtu.be/IeBzkXhzLMg | H15: OK | I15: finalizado | J15: ok | K15: 2390P013684 | L15: 0.010069444
D16: AULA 14 | E16: Análise Semântica - Parte 2 | G16: https://youtu.be/NCs3Nl1ruaw | H16: OK | I16: finalizado | J16: ok | K16: 2390P013685 | L16: 0.0099421296
D17: AULA 15 | E17: Tabela de Símbolos | G17: https://youtu.be/Lbw2XSXdMfk | H17: OK | I17: finalizado | J17: ok | K17: 2390P013992 | L17: 0.013252315
C18: Semana 6 | D18: AULA 16 | E18: Geração de Código Intermedário - Parte 1 | G18: https://youtu.be/kprY66DRrfM | H18: OK | I18: finalizado | J18: ok | K18: 2390P013687 | L18: 0.011122685
D19: AULA 17 | E19: Geração de Código Intermedário - Parte 2 | G19: https://youtu.be/7-fRozxcnLs | H19: OK | I19: finalizado | J19: ok | K19: 2390P013688 | L19: 0.010960648
D20: AULA 18 | E20: Otimização de Código | G20: https://youtu.be/NIFbBdmXY7M | H20: OK | I20: finalizado | J20: ok | K20: 2390P013689 | L20: 0.012650463
C21: Semana 7 | D21: AULA 19 | E21: Gerenciamento de Memória | G21: https://youtu.be/saa-kImX_7Q | H21: OK | I21: finalizado | J21: ok | K21: 2390P013690 | L21: 0.013958333
D22: AULA 20 | E22: Exemplos de Otimização de Código | G22: https://youtu.be/ACFeqbGKm7s | H22: OK | I22: finalizado | J22: ok | K22: 2390P013691 | L22: 0.013101852
D23: AULA 21 | E23: Compiladores X Interpretadores | G23: https://youtu.be/_UW6zqpqUoM | H23: OK | I23: finalizado | J23: ok | K23: 2390P013692 | L23: 0.0097337963
A25: ADM330 | B25: Conceitos e práticas de marketing | C25: Semana 1 | D25: AULA 0 | E25: Apresentação | G25: https://youtu.be/bPCusHxXqwY | H25: OK | I25: finalizado | J25: ok | K25: 2390P013647 | L25: 0.001724537 | M25: =VLOOKUP(A25,Geral!$A$1:$D$36,3,FALSE) -> Renato da Costa dos Santos
D26: AULA 01 | E26: Fundamentos de Marketing | G26: https://youtu.be/VADtol1bGf8 | H26: OK | I26: finalizado | J26: ok | K26: 2390P014149 | L26: 0.0071296296
D27: AULA 02 | E27: Os 4Ps (produto, preço, praça e promoção). | G27: https://youtu.be/xmtxEj14A1c | H27: OK | I27: finalizado | J27: ok | K27: 2390P013599 | L27: 0.009212963
D28: AULA 03 | E28: Estratégias de segmentação de mercado e posicionamento. | G28: https://youtu.be/FfZ5G3bu-VM | H28: OK | I28: finalizado | J28: ok | K28: 2390P013600 | L28: 0.011041667
C29: Semana 2 | D29: AULA 04 | E29: Pesquisa de Mercado | G29: https://youtu.be/K8N3wtu00Ds | H29: OK | I29: finalizado | J29: ok | K29: 2390P013601 | L29: 0.012233796
D30: AULA 05 | E30: Técnicas de coleta e análise de dados no marketing | G30: https://youtu.be/6tscqcKxZnI | H30: OK | I30: finalizado | J30: ok | K30: 2390P013602 | L30: 0.0089699074
D31: AULA 06 | E31: Comportamento do consumidor e tendências de mercado | G31: https://youtu.be/WjQylXkNIAw | H31: OK | I31: finalizado | J31: ok | K31: 2390P013603 | L31: 0.012025463
C32: Semana 3 | D32: AULA 07 | E32: Marketing de busca | G32: https://youtu.be/9Lj-wIfZQ6M | H32: OK | I32: finalizado | J32: ok | K32: 2390P013604 | L32: 0.010219907
D33: AULA 08 | E33: O uso dos anúncios pagos | G33: https://youtu.be/W6PLmL27sPs | H33: OK | I33: finalizado | J33: ok | K33: 2390P013741 | L33: 0.011111111
D34: AULA 09 | E34: Estratégias de otimização de sites | G34: https://youtu.be/VDRvZgjcpVg | H34: OK | I34: finalizado | J34: ok | K34: 2390P013606 | L34: 0.0095486111
C35: Semana 4 | D35: AULA 10 | E35: Elaboração de um plano de marketing | G35: https://youtu.be/GvMV2xNMmNM | H35: OK | I35: finalizado | J35: ok | K35: 2390P014061 | L35: 0.010474537
D36: AULA 11 | E36: Identificação de metas e recursos | G36: https://youtu.be/Y0x4e96ZNmw | H36: OK | I36: finalizado | J36: ok | K36: 2390P013608 | L36: 0.010763889
D37: AULA 12 | E37: Monitoramento de desempenho | G37: https://youtu.be/p10EWseGumo | H37: OK | I37: finalizado | J37: ok | K37: 2390P013609 | L37: 0.0093402778
C38: Semana 5 | D38: AULA 13 | E38: Estratégias de marketing de serviços | G38: https://youtu.be/ZKbojGW9_So | H38: OK | I38: finalizado | J38: ok | K38: 2390P014150 | L38: 0.01130787
D39: AULA 14 | E39: Características do setor de serviços | G39: https://youtu.be/6xy1vpnkMYY | H39: OK | I39: finalizado | J39: ok | K39: 2390P014151 | L39: 0.011481481
D40: AULA 15 | E40: Marketing de relacionamento | G40: https://youtu.be/sCvG0WEIjDA | H40: OK | I40: finalizado | J40: ok | K40: 2390P014152 | L40: 0.0091898148
C41: Semana 6 | D41: AULA 16 | E41: Marketing tradicional e o marketing digital | F41: Com arte | G41: https://youtu.be/pmZ7y5W7AGg | H41: OK | I41: finalizado | J41: ok | K41: 2390P014590 | L41: 0.0077314815
D42: AULA 17 | E42: As plataformas e os canais digitais | G42: https://youtu.be/FQ29eXQZeeU | H42: OK | I42: finalizado | J42: ok | K42: 2390P013614 | L42: 0.011030093
D43: AULA 18 | E43: Estratégias de marketing digital, como redes sociais, e-mail marketing e marketing de conteúdo. | G43: https://youtu.be/KBiU5Hge0oY | H43: OK | I43: finalizado | J43: ok | K43: 2390P013615 | L43: 0.011064815
C44: Semana 7 | D44: AULA 19 | E44: Aprender a utilizar ferramentas de análise de dados no contexto do marketing. | F44: Com arte | G44: https://youtu.be/QeZOYhYFR7E | H44: OK | I44: finalizado | J44: ok | K44: 2390P013616 | L44: 0.0064236111
D45: AULA 20 | E45: Utilização de ferramentas de análise de dados no marketing | G45: https://youtu.be/FfBohIWWb-A | H45: OK | I45: finalizado | J45: ok | K45: 2390P013617 | L45: 0.0088194444
D46: AULA 21 | E46: Desenvolver habilidades para medir e avaliar o desempenho das estratégias de marketing com base nos dados coletados | G46: https://youtu.be/hjurTPiF_Fg | H46: OK | I46: finalizado | J46: ok | K46: 2390P013618 | L46: 0.0077777778
A48: ADM320 | B48: Gestão da Produção e Operações | C48: Semana 1 | D48: AULA 0 | E48: Apresentação | G48: https://youtu.be/yjEcmCJeLZI | H48: Ok | I48: finalizado | J48: ok | K48: 2390P013695 | L48: 0.0014699074 | M48: =VLOOKUP(A48,Geral!$A$1:$D$36,3,FALSE) -> Renato da Costa dos Santos
D49: AULA 01 | E49: Estudar os conceitos básicos da administração da produção e operações | G49: https://youtu.be/s6Qx6Emie1M | H49: Ok | I49: finalizado | J49: ok | K49: 2390P013696 | L49: 0.013784722
D50: AULA 02 | E50: Compreender os princípios e objetivos da gestão da qualidade | G50: https://youtu.be/RStenZ0btAo | H50: Ok | I50: finalizado | J50: ok | K50: 2390P013697 | L50: 0.011076389
D51: AULA 03 | E51: Familiarizar-se com os sistemas de produção enxuta e sua aplicação | G51: https://youtu.be/uSaOps8hZRk | H51: Ok | I51: finalizado | J51: ok | K51: 2390P013698 | L51: 0.010659722
C52: Semana 2 | D52: AULA 04 | E52: Monitoramento e desempenho | G52: https://youtu.be/FZTdqS68gtw | H52: Ok | I52: finalizado | J52: ok | K52: 2390P013699 | L52: 0.012986111
D53: AULA 05 | E53: Programação e Sequenciamento de Atividades Produtivas | G53: https://youtu.be/f0TNILztUXw | H53: Ok | I53: finalizado | J53: ok | K53: 2390P013700 | L53: 0.012766204
D54: AULA 06 | E54: Técnicas de controle da produção | G54: https://youtu.be/j2aJG4OHPKQ | H54: Ok | I54: finalizado | J54: ok | K54: 2390P013701 | L54: 0.014409722
C55: Semana 3 | D55: AULA 07 | E55: Técnicas para determinação de níveis de estoque ideais | G55: https://youtu.be/D__RkqqAmp0 | H55: Ok | I55: finalizado | J55: ok | K55: 2390P013702 | L55: 0.013287037
D56: AULA 08 | E56: Políticas de reposição de estoque e sistemas de controle de estoque eficientes. | G56: https://youtu.be/uW2ZSoGOYXw | H56: Ok | I56: finalizado | J56: ok | K56: 2390P013703 | L56: 0.012719907
D57: AULA 09 | E57: Tipos de estoque e suas funções na cadeia de suprimentos. | G57: https://youtu.be/jndqowMlybk | H57: Ok | I57: finalizado | J57: ok | K57: 2390P013704 | L57: 0.012858796
C58: Semana 4 | D58: AULA 10 | E58: Análises de capacidade produtiva e seus gargalos. | G58: https://youtu.be/29RaLQQxR-M | H58: Ok | I58: finalizado | J58: ok | K58: 2390P013705 | L58: 0.012708333
D59: AULA 11 | E59: Balanceamento de carga de trabalho e alocação de recursos | G59: https://youtu.be/Lc7E3Tpj0jY | H59: Ok | I59: finalizado | J59: ok | K59: 2390P013706 | L59: 0.010497685
D60: AULA 12 | E60: Técnicas de dimensionamento de capacidade, considerando demandas sazonais e estratégias de crescimento | G60: https://youtu.be/CUY19o0E-M0 | H60: Ok | I60: finalizado | J60: ok | K60: 2390P013707 | L60: 0.01
C61: Semana 5 | D61: AULA 13 | E61: Estratégias de aquisição e gestão de materiais | G61: https://youtu.be/tVt8-mv5-Iw | H61: Ok | I61: finalizado | J61: ok | K61: 2390P013708 | L61: 0.0090856481
D62: AULA 14 | E62: Sistemas de controle de ativos e recursos patrimoniais. | G62: https://youtu.be/b-1v9qyS0pk | H62: Ok | I62: finalizado | J62: ok | K62: 2390P013709 | L62: 0.0082175926
D63: AULA 15 | E63: Negociação e gestão de contratos com fornecedores. | G63: https://youtu.be/Ap-fi_vALwQ | H63: Ok | I63: finalizado | J63: ok | K63: 2390P013710 | L63: 0.0080787037
C64: Semana 6 | D64: AULA 16 | E64: Princípios e funcionalidades de sistemas de gestão integrada | G64: https://youtu.be/_l0c9nXvRqQ | H64: Ok | I64: finalizado | J64: ok | K64: 2390P013711 | L64: 0.0090856481
D65: AULA 17 | E65: Planejamento e controle das atividades de produção, estoque e suprimentos. | G65: https://youtu.be/-hqzCfHMaDA | H65: Ok | I65: finalizado | J65: ok | K65: 2390P013712 | L65: 0.0090972222
D66: AULA 18 | E66: Análise de dados e tomada de decisão com base nas informações geradas pelos sistemas. | G66: https://youtu.be/fy1KvQUaxHw | H66: Ok | I66: finalizado | J66: ok | K66: 2390P013713 | L66: 0.0089930556
C67: Semana 7 | D67: AULA 19 | E67: Estudos de caso e Projetos práticos. | G67: https://youtu.be/2q-sbPUv01c | H67: Ok | I67: finalizado | J67: ok | K67: 2390P013714 | L67: 0.0086921296
D68: AULA 20 | E68: Estratégias de administração da produção e operações em empresas | F68: com arte | G68: https://youtu.be/53U4tEed78E | H68: Ok | I68: finalizado | J68: ok | K68: 2390P013715 | L68: 0.0061921296
D69: AULA 21 | E69: Desafios e oportunidade na gestão da produção e operações em diferentes setores e contextos organizacionais | F69: com arte | G69: https://youtu.be/s72rYqYDzWg | H69: Ok | I69: finalizado | J69: ok | K69: 2390P013716 | L69: 0.0070717593
A71: PES320 | B71: Controle Estatístico e Gestão da Qualidade | C71: Semana 1 | D71: AULA 0 | E71: Apresentação | G71: https://youtu.be/Ik8Yu_ZLz3w | H71: OK | I71: finalizado | J71: ok | K71: 2390P013717 | L71: 0.0015046296 | M71: =VLOOKUP(A71,Geral!$A$1:$D$36,3,FALSE) -> Marco Aurélio Soares De Castro
D72: AULA 01 | E72: Estatística e Engenharia | G72: https://youtu.be/Rod-sPEvegw | H72: OK | I72: finalizado | J72: ok | K72: 2390P013718 | L72: 0.013148148
D73: AULA 02 | E73: Qualidade: Controle da Qualidade | G73: https://youtu.be/9wEbfAh8HRw | H73: OK | I73: finalizado | J73: ok | K73: 2390P013719 | L73: 0.012071759
D74: AULA 03 | E74: Controle Estatístico de Processo - Conceitos | G74: https://youtu.be/vjsJTkjwa-M | H74: OK | I74: finalizado | J74: ok | K74: 2390P014337 | L74: 0.021215278
C75: Semana 2 | D75: AULA 04 | E75: Análise e priorização de problemas - o princípio de Pareto | G75: https://youtu.be/76LvKK6bLu0 | H75: OK | I75: finalizado | J75: ok | K75: 2390P014591 | L75: 0.0078703704
D76: AULA 05 | E76: O Diagrama de Pareto - construção | G76: https://youtu.be/wHOC5GV0RpY | H76: OK | I76: finalizado | J76: ok | K76: 2390P014592 | L76: 0.012638889
D77: AULA 06 | E77: Diagrama de Pareto: exemplos de aplicação | G77: https://youtu.be/qyF8V_nBXEc | H77: OK | I77: finalizado | J77: ok | K77: 2390P013723 | L77: 0.013333333
C78: Semana 3 | D78: AULA 07 | E78: Kaoru Ishikawa e as Ferramentas da Qualidade | G78: https://youtu.be/zr79A7aTu3A | H78: OK | I78: finalizado | J78: ok | K78: 2390P013724 | L78: 0.0068865741
D79: AULA 08 | E79: O Diagrama de Ishikawa | G79: https://youtu.be/6de6iREpX-A | H79: OK | I79: finalizado | J79: ok | K79: 2390P013725 | L79: 0.014212963
D80: AULA 09 | E80: Diagrama de Ishikawa: exemplos de aplicação | G80: https://youtu.be/Th1j6OlTO5M | H80: OK | I80: finalizado | J80: ok | K80: 2390P013726 | L80: 0.010243056
C81: Semana 4 | D81: AULA 10 | E81: Shewhart e o CEP / gráfico de controle | G81: https://youtu.be/hOpSz2Ab7J0 | H81: OK | I81: finalizado | J81: ok | K81: 2390P013727 | L81: 0.01275463
D82: AULA 11 | E82: Tipos de Gráficos de Controle | G82: https://youtu.be/LrfLtFWv6O0 | H82: OK | I82: finalizado | J82: ok | K82: 2390P013728 | L82: 0.014814815
D83: AULA 12 | E83: Gráficos de Controle: exemplos de aplicação | G83: https://youtu.be/AB8YZ42INfo | H83: OK | I83: finalizado | J83: ok | K83: 2390P013729 | L83: 0.013993056
C84: Semana 5 | D84: AULA 13 | E84: Inspeção da qualidade | G84: https://youtu.be/dRKgO5cSOW4 | H84: OK | I84: finalizado | J84: ok | K84: 2390P014155 | L84: 0.014803241
D85: AULA 14 | E85: Índices de capacidade de processos | G85: https://youtu.be/fhWRfZA9n50 | H85: OK | I85: finalizado | J85: ok | K85: 2390P013731 | L85: 0.015185185
D86: AULA 15 | E86: Inspeção da qualidade e Capacidade de processos: exemplos de aplicação | G86: https://youtu.be/HAW1cztNtgo | H86: OK | I86: finalizado | J86: ok | K86: 2390P013732 | L86: 0.012071759
C87: Semana 6 | D87: AULA 16 | E87: Gestão da Qualidade: evolução dos conceitos | G87: https://youtu.be/MUwb57TbON0 | H87: OK | I87: finalizado | J87: ok | K87: 2390P014306 | L87: 0.014548611
D88: AULA 17 | E88: Normas referente à Gestão da Qualidade | G88: https://youtu.be/ua5kjS5D3Aw | H88: OK | I88: finalizado | J88: ok | K88: 2390P013734 | L88: 0.014166667
D89: AULA 18 | E89: Melhoria Continua e Certificações | G89: https://youtu.be/kZh2T6cmKnc | H89: OK | I89: finalizado | J89: ok | K89: 2390P013735 | L89: 0.012638889
C90: Semana 7 | D90: AULA 19 | E90: Ferramentas da qualidade - Parte I | G90: https://youtu.be/Sp2W085rrVE | H90: OK | I90: finalizado | J90: ok | K90: 2390P013736 | L90: 0.014884259
D91: AULA 20 | E91: Ferramentas da qualidade - Parte II | G91: https://youtu.be/Nz5h6JumQpY | H91: OK | I91: finalizado | J91: ok | K91: 2390P013737 | L91: 0.014814815
D92: AULA 21 | E92: PDCA e MASP | G92: https://youtu.be/NC067oAuXH4 | H92: OK | I92: finalizado | J92: ok | K92: 2390P013738 | L92: 0.012453704
A94: SAA001 | B94: Avaliação Educacional e da Aprendizagem | D94: AULA 01 | E94: Contextualização da avaliação Educacional | G94: https://youtu.be/Ov3G1rdD6sw | H94: ok | I94: finalizado | J94: ok | K94: 2390P013344 | L94: 0.016805556
D95: AULA 02 | E95: Avaliação Institucional Participativa | G95: https://youtu.be/Uuaf3yyvsvM | H95: - | I95: finalizado | J95: ok | K95: 2390P013345 | L95: 0.013541667
D96: AULA 03 | E96: Avaliação educacional na educação básica | G96: https://youtu.be/0NectYtASvQ | H96: - | I96: finalizado | J96: ok | K96: 2390P013346 | L96: 0.010104167
C97: Semana 2 | D97: AULA 04 | E97: Avaliação da Aprendizagem | G97: https://youtu.be/4gJvmo8oYeg | H97: ok | I97: finalizado | J97: ok | K97: 2390P013347 | L97: 0.0092476852
D98: AULA 05 | E98: Avaliação da Aprendizagem - perspectivas teóricas | G98: https://youtu.be/kZH7f_DPQdQ | H98: - | I98: finalizado | J98: ok | K98: 2390P013348 | L98: 0.013159722
D99: AULA 06 | E99: Avaliação da Aprendizagem na prática | G99: https://youtu.be/pgv6r6XLV3U | H99: ok | I99: finalizado | J99: ok | K99: 2390P013349 | L99: 0.0098032407
C100: Semana 3 | D100: AULA 07 | E100: Critérios e instrumentos de avaliação | G100: https://youtu.be/nTqA3LWljuk | H100: ok | I100: finalizado | J100: ok | K100: 2390P014594 | L100: 0.0084953704
D101: AULA 08 | E101: Critérios e instrumentos de avaliação II | G101: https://youtu.be/V2QRXePhD6Y | H101: ok | I101: finalizado | J101: ok | K101: 2390P013351 | L101: 0.0079398148
D102: AULA 09 | E102: Critérios e instrumentos de avaliação III | G102: https://youtu.be/9ocnZKUNGwg | H102: ok | I102: finalizado | J102: ok | K102: 2390P013352 | L102: 0.016261574
C103: Semana 4 | D103: AULA 10 | E103: Do currículo à avaliação ou da avaliação ao currículo | G103: https://youtu.be/ruPo-ew3Adg | H103: - | I103: finalizado | J103: ok | K103: 2390P013353 | L103: 0.015578704
D104: AULA 11 | E104: A inter-relação entre currículo e avaliação | G104: https://youtu.be/aaKDPs8z3jI | H104: - | I104: finalizado | J104: ok | K104: 2390P013354 | L104: 0.014525463
...

Sheet 2024.3
A1: CÓD | B1: Disciplina | C1: Semanas | D1: Nº de aulas | E1: Título da aula | F1: Sinopse da Videoaula | G1: Link no YouTube | H1: Slide na pasta | I1: Status | J1: Download | K1: ID (TV Cultura) | L1: Duração | M1: Professor | N1: DI
A2: ADM400 | B2: =VLOOKUP(A2,Geral!$A$1:$D$36,2,FALSE) -> Cidades Inteligentes | C2: Semana 1 | D2: AULA 0 | E2: Apresentação | G2: https://youtu.be/IuAQUTz_wTg | I2: finalizado | J2: ok | K2: 2390P014529 | L2: 0.0021296296 | M2: =VLOOKUP(A2,Geral!$A$1:$D$36,3,FALSE) -> Júlio Cezar Estrella | N2: =VLOOKUP(A2,Geral!$A$1:$D$36,4,FALSE) -> Daniel
D3: AULA 01 | E3: O que é uma Cidade Inteligente | G3: https://youtu.be/D4LFTdym7Oc | H3: Ok | I3: finalizado | J3: ok | K3: 2390P015132 | L3: 0.014918981
D4: AULA 02 | E4: O Papel da Gestão Pública nas Cidades Inteligentes | G4: https://youtu.be/9UctkXhcZM8 | H4: Ok | I4: finalizado | J4: ok | K4: 2390P015133 | L4: 0.014016204
D5: AULA 03 | E5: Desafios em Aberto nas Cidades Inteligentes | G5: https://youtu.be/TXqfsocBNUg | H5: Ok | I5: finalizado | J5: ok | K5: 2390P015134 | L5: 0.011377315
C6: Semana 2 | D6: AULA 04 | E6: Dados Abertos: Conceitos Fundamentais e Exemplos de Aplicações | G6: https://youtu.be/Lo8GIm9Ley4 | H6: Ok | I6: finalizado | J6: ok | K6: 2390P015135 | L6: 0.011284722
D7: AULA 05 | E7: Interoperabilidade em Cidades Inteligentes – Parte 1 | G7: https://youtu.be/ivTUbwrvB88 | H7: Ok | I7: finalizado | J7: ok | K7: 2390P015136 | L7: 0.01375
D8: AULA 06 | E8: Interoperabilidade em Cidades Inteligentes – Parte 2 | G8: https://youtu.be/BbXMgBkLK-A | H8: Ok | I8: finalizado | J8: ok | K8: 2390P015137 | L8: 0.0099421296
C9: Semana 3 | D9: AULA 07 | E9: Introdução ao Conceito de Interdisciplinaridade | G9: https://youtu.be/N9thu-48Ck8 | H9: Ok | I9: finalizado | J9: ok | K9: 2390P015138 | L9: 0.013518519
D10: AULA 08 | E10: Casos Práticos de Colaboração em Projetos Urbanos | G10: https://youtu.be/eJ207ATMsf0 | H10: Ok | I10: finalizado | J10: ok | K10: 2390P015139 | L10: 0.01130787
D11: AULA 09 | E11: Estratégias para superar Desafios na Implementação Interdisciplinar | G11: https://youtu.be/6l2fCwAeEMQ | H11: Ok | I11: finalizado | J11: ok | K11: 2390P015140 | L11: 0.0072916667
C12: Semana 4 | D12: AULA 10 | E12: Princípios de Internet das Coisas e suas Aplicações | G12: https://youtu.be/IHgSqg6kIew | H12: Ok | I12: finalizado | J12: ok | K12: 2390P015141 | L12: 0.013796296
D13: AULA 11 | E13: BigData: Análise das Características e Importância na Gestão Urbana | G13: https://youtu.be/tkyqf8JuIww | H13: Ok | I13: finalizado | J13: ok | K13: 2390P015142 | L13: 0.013148148
D14: AULA 12 | E14: Sistemas Distribuídos: Estratégias para lidar com a Escalabilidade em Ambientes Urbanos | G14: https://youtu.be/JrwqwU8ZaPw | H14: Ok | I14: finalizado | J14: ok | K14: 2390P015143 | L14: 0.013865741
C15: Semana 5 | D15: AULA 13 | E15: Ferramentas de Gestão e a utilização no gerenciamento de cidades inteligentes | G15: https://youtu.be/7FXRwxJFj_E | H15: Ok | I15: finalizado | J15: ok | K15: 2390P015144 | L15: 0.014502315
D16: AULA 14 | E16: Ferramentas Computacionais para o desenvolvimento de soluções para Cidades Inteligentes - Parte 1 | G16: https://youtu.be/8pPRLC0UWNI | H16: Ok | I16: finalizado | J16: ok | K16: 2390P015145 | L16: 0.01349537
D17: AULA 15 | E17: Ferramentas Computacionais para o desenvolvimento de soluções para Cidades Inteligentes - Parte 2 | G17: https://youtu.be/60DzT5wx5Gg | H17: Ok | I17: finalizado | J17: ok | K17: 2390P015146 | L17: 0.013773148
C18: Semana 6 | D18: AULA 16 | E18: O que é Simulação: Visão geral dos conceitos básicos de simulação | G18: https://youtu.be/y7U1rtTaxLU | H18: Ok | I18: finalizado | J18: ok | K18: 2390P015147 | L18: 0.01099537
D19: AULA 17 | E19: Simulação em Larga Escala: Desafios e Benefícios | G19: https://youtu.be/UFZRB7X_tkA | H19: Ok | I19: finalizado | J19: ok | K19: 2390P015148 | L19: 0.011099537
D20: AULA 18 | E20: Simulação no Contexto do Planejamento Urbano | G20: https://youtu.be/6VLZh7zpQ_w | H20: Ok | I20: finalizado | J20: ok | K20: 2390P015149 | L20: 0.010081019
C21: Semana 7 | D21: AULA 19 | E21: Tecnologias em Cidades Inteligentes: sensores | G21: https://youtu.be/zbZL69eYsZg | H21: Ok | I21: finalizado | J21: ok | K21: 2390P015150 | L21: 0.014363426
D22: AULA 20 | E22: Tecnologias em Cidades Inteligentes: Computação em Nuvem | G22: https://youtu.be/vnXlIimJnVM | H22: Ok | I22: finalizado | J22: ok | K22: 2390P015151 | L22: 0.011331019
D23: AULA 21 | E23: Tecnologias em Cidades Inteligentes: Inteligência Artificial (IA) | G23: https://youtu.be/yRZqk-Ua6Zw | H23: Ok | I23: finalizado | J23: ok | K23: 2390P015152 | L23: 0.012592593
A25: SCN001 | B25: =VLOOKUP(A25,Geral!$A$1:$D$36,2,FALSE) -> Fundamentos e práticas no ensino de Ciências da Natureza | C25: Semana 1 | D25: AULA 0 | E25: Apresentação | G25: https://youtu.be/4KU7Whs3ZyE | H25: ok | I25: finalizado | J25: ok | K25: 2390P014308 | L25: 0.0016550926 | M25: =VLOOKUP(A25,Geral!$A$1:$D$36,3,FALSE) -> Juliana Hanna Leite El Ottra | N25: =VLOOKUP(A25,Geral!$A$1:$D$36,4,FALSE) -> Vanessa
D26: AULA 01 | E26: Introdução à ciência (parte I) | G26: https://youtu.be/v4P_zDx62L0 | H26: ok | I26: finalizado | J26: ok | K26: 2390P014309 | L26: 0.014548611
D27: AULA 02 | E27: Introdução à ciência (parte II) | G27: https://youtu.be/g-Q8j2aY-iw | H27: ok | I27: finalizado | J27: ok | K27: 2390P014601 | L27: 0.014479167
D28: AULA 03 | E28: O método científico e o ensino de ciências por investigação | G28: https://youtu.be/BlR0ANkVvX0 | H28: ok | I28: finalizado | J28: ok | K28: 2390P014310 | L28: 0.014652778
C29: Semana 2 | D29: AULA 04 | E29: O desenvolvimento histórico dos estudos astronômicos | G29: https://youtu.be/FnPBZu_lvp4 | H29: ok | I29: finalizado | J29: ok | K29: 2390P014311 | L29: 0.014479167
D30: AULA 05 | E30: O desenvolvimento histórico dos estudos astronômicos (parte II)/ a astronomia do século XXI | G30: https://youtu.be/KPDlU9U7K9g | H30: ok | I30: finalizado | J30: ok | K30: 2390P014312 | L30: 0.0146875
D31: AULA 06 | E31: A relação entre a ciência e a religião, e sua relação com mudanças de paradigmas científicos | G31: https://youtu.be/8uj92HEG9ag | H31: ok | I31: finalizado | J31: ok | K31: 2390P014602 | L31: 0.014930556
C32: Semana 3 | D32: AULA 07 | E32: As quatro perspectivas entre Ciência e Religião | G32: https://youtu.be/GZ9QGxY2sqc | H32: ok | I32: finalizado | J32: ok | K32: 2390P014603 | L32: 0.013715278
D33: AULA 08 | E33: O desenvolvimento da Ciências da Terra e os processos tectônicos | G33: https://youtu.be/eH_6jkGvZKQ | H33: ok | I33: finalizado | J33: ok | K33: 2390P014044 | L33: 0.013715278
D34: AULA 09 | E34: A geologia e o meio ambiente | G34: https://youtu.be/wY6BgOn5rP4 | H34: ok | I34: finalizado | J34: ok | K34: 2390P014045 | L34: 0.014131944
C35: Semana 4 | D35: AULA 10 | E35: O efeito estufa e as mudanças climáticas: Parte I - Problemas ambientais do século XXI e a relação com a Ciência e sociedade | G35: https://youtu.be/VDueqEGF09Y | H35: ok | I35: finalizado | J35: ok | K35: 2390P014046 | L35: 0.014386574
D36: AULA 11 | E36: Os recursos hídricos: Parte II - Problemas ambientais do século XXI e a relação com a Ciência e sociedade | G36: https://youtu.be/PLQCk6AbC_0 | H36: ok | I36: finalizado | J36: ok | K36: 2390P014604 | L36: 0.014618056
D37: AULA 12 | E37: O problema do lixo: Parte III - Problemas ambientais do século XXI e a relação com a Ciência e sociedade | G37: https://youtu.be/9Lu-iAlWs4Q | H37: ok | I37: finalizado | J37: ok | K37: 2390P014048 | L37: 0.014027778
C38: Semana 5 | D38: AULA 13 | E38: O desenvolvimento da Biologia Molecular e a compreensão da vida | G38: https://youtu.be/vU3qKI6-jhw | H38: ok | I38: finalizado | J38: ok | K38: 2390P014049 | L38: 0.013680556
D39: AULA 14 | E39: Biotecnologia e Bioética | G39: https://youtu.be/wzZGAZ7Zv40 | H39: ok | I39: finalizado | J39: ok | K39: 2390P014050 | L39: 0.014606481
C40: Semana 6 | D40: AULA 15 | E40: A leitura crítica de obras científicas | G40: https://youtu.be/1F44bW2j6wI | H40: ok | I40: finalizado | J40: ok | K40: 2390P014605 | L40: 0.014490741
D41: AULA 16 | E41: A comunicação científica | G41: https://youtu.be/bODgK7Cs5og | H41: ok | I41: finalizado | J41: ok | K41: 2390P014052 | L41: 0.014791667
D42: AULA 17 | I42: vai gravar
D43: AULA 18 | I43: vai gravar
C44: Semana 7 | D44: AULA 19 | I44: vai gravar
D45: AULA 20 | I45: vai gravar
D46: AULA 21 | I46: vai gravar
A48: PJI500 | B48: =VLOOKUP(A48,Geral!$A$1:$D$36,2,FALSE) -> Projeto Integrador II - Negócios e Produção | C48: Quinzena 1 | D48: AULA 0 | E48: Apresentação | G48: https://youtu.be/jz16A0Hq0JM | H48: Ok | I48: finalizado | J48: ok | K48: 2390P014630 | L48: 0.0013425926 | M48: =VLOOKUP(A48,Geral!$A$1:$D$36,3,FALSE) -> Antonio Francisco Savi | N48: =VLOOKUP(A48,Geral!$A$1:$D$36,4,FALSE) -> Alfredo
D49: AULA 01 | E49: Resumo geral do Projeto Integrador | F49: Nesta videoaula, o professor Antonio Francisco Savi faz uma breve explanação sobre o que a Univesp espera como resultado do Projeto Integrador. | G49: https://youtu.be/WS1WfwfoiT4 | H49: Ok | I49: finalizado | J49: ok | K49: 2390P014631 | L49: 0.011076389
D50: AULA 02 | E50: Concepção do projeto | F50: Esta videoaula do professor Antonio Francisco Savi apresenta o conceito de processo de negócio e destaca a importância de mapear os processos. | G50: https://youtu.be/iiZTKq_eZSI | H50: Ok | I50: finalizado | J50: ok | K50: 2390P014632 | L50: 0.013090278
C51: Quinzena 2 | D51: AULA 03 | E51: Por que mapear processo? | F51: O professor Antonio Francisco Savi, nesta videoaula, apresenta as razões para o mapeamento de processos, iniciando por se conhecer os processos atuais, passando por identificar oportunidades, criar e implantar soluções em vista de um aperfeiçoamento contínuo. | G51: https://youtu.be/YAY1qttcGa4 | H51: Ok | I51: finalizado | J51: ok | K51: 2390P014633 | L51: 0.009525463
D52: AULA 04 | E52: Lean Production | F52: Nesta videoaula, o professor Antonio Francisco Savi apresenta os conceitos e métodos de produção enxuta (lean production) e de mapeamento de processos. | G52: https://youtu.be/8c65xWDkBwo | I52: finalizado | J52: ok | K52: 2390P014634 | L52: 0.0084375
C53: Quinzena 3 | D53: AULA 05 | E53: Melhores práticas e exemplos de modelagem | F53: Nesta videoaula, o professor Antonio Francisco Savi aborda o conceito de melhores práticas, partindo da apresentação do software BPM (business process modeling) Aris. | G53: https://youtu.be/MrVPbrgdK7E | H53: Ok | I53: finalizado | J53: ok | K53: 2390P014635 | L53: 0.0086111111
C54: Quinzena 4 | D54: AULA 06 | E54: Ferramentas e métodos para confecção do protótipo | F54: “Ferramentas e métodos para a confecção do protótipo” é o tema desta videoaula do professor Antonio Francisco Savi. A partir de uma primeira conceituação, são apresentados os principais tipos de protótipo e, em seguida, a aplicação do protótipo no tema do Projeto Integrador. | G54: https://youtu.be/qXrxaTkFkEY | H54: Ok | I54: finalizado | J54: ok | K54: 2390P014636 | L54: 0.0078703704
C55: Quinzena 5 | D55: AULA 07 | E55: Melhoria da solução | F55: O professor Antonio Francisco Savi, nesta videoaula, iniciando dizendo que o processo de melhoria da solução deve ocorrer durante todo o seu desenvolvimento. Em seguida fala os pontos principais do que devem ser levados em conta na melhoria de processo e compara o ciclo PDCA e o ciclo SDCA. | G55: https://youtu.be/ySlWGLRIi5o | H55: Ok | I55: finalizado | J55: ok | K55: 2390P014637 | L55: 0.0090509259
A57: ADM350 | B57: =VLOOKUP(A57,Geral!$A$1:$D$36,2,FALSE) -> Aprendizagem e gestão do conhecimento | C57: Semana 1 | D57: AULA 0 | E57: Apresentação | G57: https://youtu.be/HEw2qui9gXc | H57: Ok | I57: finalizado | J57: ok | K57: 2390P014599 | L57: 0.0017708333 | M57: =VLOOKUP(A57,Geral!$A$1:$D$36,3,FALSE) -> Cíntia Cristina Silva de Araújo | N57: =VLOOKUP(A57,Geral!$A$1:$D$36,4,FALSE) -> Ieda
D58: AULA 01 | E58: Aprendizagem individual e coletiva | G58: https://youtu.be/14SKIsLb76k | H58: Ok | I58: finalizado | J58: ok | K58: 2390P014289 | L58: 0.016319444
D59: AULA 02 | E59: Conceitos importantes da gestão estratégica do conhecimento | G59: https://youtu.be/pNES9zvBU7I | H59: Ok | I59: finalizado | J59: ok | K59: 2390P014290 | L59: 0.015532407
D60: COST 2 | E60: Costurando semana 02 | G60: https://youtu.be/b-RvjhaSSt8 | I60: finalizado | J60: ok | K60: 2390P014446 | L60: 0.0018402778
C61: Semana 3 | D61: AULA 03 | E61: Importância da aprendizagem organizacional em tempos turbulentos | G61: https://youtu.be/tt-04GP1wSQ | H61: Ok | I61: finalizado | J61: ok | K61: 2390P014291 | L61: 0.015173611
D62: AULA 04 | E62: Introdução ao planejamento estratégico | G62: https://youtu.be/McEOJaSOZSM | H62: Ok | I62: finalizado | J62: ok | K62: 2390P014292 | L62: 0.015335648
D63: AULA 05 | E63: Ciclos de aprendizagem e desenvolvimento de competências | G63: https://youtu.be/xG2Bz8EiXxE | H63: Ok | I63: finalizado | J63: ok | K63: 2390P014293 | L63: 0.015034722
C64: Semana 4 | D64: AULA 06 | E64: O que é ESG? | G64: https://youtu.be/sdeZJWto9vE | H64: Ok | I64: finalizado | J64: ok | K64: 2390P014294 | L64: 0.015439815
D65: AULA 07 | E65: Barreiras e facilitadores ao processo de aprendizagem | G65: https://youtu.be/742YloFnKTs | H65: Ok | I65: finalizado | J65: ok | K65: 2390P014295 | L65: 0.015451389
D66: AULA 08 | E66: Como criar um ambiente de trabalho favorável à aprendizagem organizacional | G66: https://youtu.be/gEOed_94evQ | H66: Ok | I66: finalizado | J66: ok | K66: 2390P014296 | L66: 0.016076389
C67: Semana 5 | D67: AULA 09 | E67: As organizações do conhecimento | G67: https://youtu.be/LYtxzC7NAP4 | H67: Ok | I67: finalizado | J67: ok | K67: 2390P014297 | L67: 0.015138889
D68: AULA 10 | E68: Papel do conhecimento e da aprendizagem nos resultados organizacionais | G68: https://youtu.be/VOwkuc1B5Oc | H68: Ok | I68: finalizado | J68: ok | K68: 2390P014298 | L68: 0.014131944
D69: AULA 11 | E69: Modelo de Conversão do Conhecimento de Nonaka | G69: https://youtu.be/q60R3wq810o | H69: Ok | I69: finalizado | J69: ok | K69: 2390P014299 | L69: 0.016284722
D70: COST 6 | E70: Costurando semana 06 | G70: https://youtu.be/ma0tMzhJngo | I70: finalizado | J70: ok | K70: 2390P014447 | L70: 0.0018055556
C71: Semana 6 | D71: AULA 12 | E71: Desenvolvendo a cultura da Gestão do Conhecimento para promoção da inovação | G71: https://youtu.be/ca5XlOV1KkQ | H71: Ok | I71: finalizado | J71: ok | K71: 2390P014300 | L71: 0.014282407
D72: AULA 13 | E72: Condições organizacionais para implementação da Gestão do Conhecimento e Capacidade Absortiva | G72: https://youtu.be/kia27Njrbmw | H72: Ok | I72: finalizado | J72: ok | K72: 2390P014301 | L72: 0.014386574
D73: AULA 14 | E73: Papel da análise interna para construção da Gestão do Conhecimento | G73: https://youtu.be/IaAu6nYZb1k | H73: Ok | I73: finalizado | J73: ok | K73: 2390P014302 | L73: 0.0140625
C74: Semana 7 | D74: AULA 15 | E74: Ferramentas de Tecnologia da Informação para a Gestão do Conhecimento | G74: https://youtu.be/xoZ5Coec5xg | H74: Ok | I74: finalizado | J74: ok | K74: 2390P014303 | L74: 0.014050926
D75: AULA 16 | E75: Lições aprendidas integrando tecnologia e base de conhecimento | G75: https://youtu.be/Fe7CzNrZ2hU | H75: Ok | I75: finalizado | J75: ok | K75: 2390P014304 | L75: 0.014166667
D76: AULA 17 | E76: Utilizando os sistemas de CRM para desenvolver inovação e capacidade de marketing | G76: https://youtu.be/puqWl6jIUy0 | H76: Ok | I76: finalizado | J76: ok | K76: 2390P014305 | L76: 0.01443287
D77: COST 8 | E77: Costurando semana 08 | G77: https://youtu.be/4ivdEG7bkjI | I77: finalizado | J77: ok | K77: 2390P014448 | L77: 0.0014814815
A79: ADM340 | B79: =VLOOKUP(A79,Geral!$A$1:$D$36,2,FALSE) -> Estratégias Financeiras | C79: Semana 1 | D79: AULA 0 | E79: Apresentação | G79: https://youtu.be/KGAikxKur_M | I79: finalizado | J79: ok | K79: 2390P013963 | L79: 0.0016203704 | M79: =VLOOKUP(A79,Geral!$A$1:$D$36,3,FALSE) -> Roberto Alexandre Zanchetta Borghi | N79: =VLOOKUP(A79,Geral!$A$1:$D$36,4,FALSE) -> Mirtes
D80: AULA 01 | E80: Introdução à disciplina de Estratégias Financeiras | G80: https://youtu.be/PHArkxHYmu0 | H80: ok | I80: finalizado | J80: ok | K80: 2390P013964 | L80: 0.016111111
D81: AULA 02 | E81: Gestão financeira: objetivos e conceitos básicos | G81: https://youtu.be/95skfr3pIoI | H81: ok | I81: finalizado | J81: ok | K81: 2390P013965 | L81: 0.018425926
D82: AULA 03 | E82: Tomada de decisões financeiras | G82: https://youtu.be/BSaH7pdN5ck | H82: ok | I82: finalizado | J82: ok | K82: 2390P013966 | L82: 0.013287037
C83: Semana 2 | D83: AULA 04 | E83: Demonstrações financeiras: análise vertical e horizontal | G83: https://youtu.be/gipINq3jEDU | H83: ok | I83: finalizado | J83: ok | K83: 2390P013967 | L83: 0.012488426
D84: AULA 05 | E84: Métricas financeiras: indicadores de liquidez, rentabilidade e endividamento | G84: https://youtu.be/FHODlkPUbDs | H84: ok | I84: finalizado | J84: ok | K84: 2390P013968 | L84: 0.012152778
D85: AULA 06 | E85: Métricas financeiras na prática: calculando os indicadores | G85: https://youtu.be/C-zvhpnxFUU | H85: ok | I85: finalizado | J85: ok | K85: 2390P013969 | L85: 0.010451389
C86: Semana 3 | D86: AULA 07 | E86: Componentes do capital de giro da empresa | G86: https://youtu.be/EGU4zjK8Eu8 | H86: ok | I86: finalizado | J86: ok | K86: 2390P013970 | L86: 0.010520833
D87: AULA 08 | E87: Estratégias para gerenciar capital de giro: otimização do ciclo de caixa | G87: https://youtu.be/l8IgDrpuY7U | H87: ok | I87: finalizado | J87: ok | K87: 2390P013971 | L87: 0.01224537
D88: AULA 09 | E88: Estratégias para gerenciar capital de giro: gestão de estoques | G88: https://youtu.be/UCGXsP10rBw | H88: ok | I88: finalizado | J88: ok | K88: 2390P013972 | L88: 0.011273148
C89: Semana 4 | D89: AULA 10 | E89: Tipos de riscos financeiros | G89: https://youtu.be/8nKxxUqPmVY | H89: ok | I89: finalizado | J89: ok | K89: 2390P013973 | L89: 0.011319444
D90: AULA 11 | E90: Técnicas de mensuração e avaliação de riscos financeiros | G90: https://youtu.be/u-RxxfnEIQ8 | H90: ok | I90: finalizado | J90: ok | K90: 2390P013974 | L90: 0.011712963
D91: AULA 12 | E91: Técnicas de mensuração e avaliação de riscos financeirosna prática: calculando os indicadores | G91: https://youtu.be/sKSXLm4Qfrg | H91: ok | I91: finalizado | J91: ok | K91: 2390P013975 | L91: 0.011226852
C92: Semana 5 | D92: AULA 13 | E92: Criação de valor na organização: o papel das decisões financeiras | G92: https://youtu.be/Qqo8ZlHuUu8 | H92: ok | I92: finalizado | J92: ok | K92: 2390P013976 | L92: 0.01224537
D93: AULA 14 | E93: ESG: Sustentabilidade e responsabilidade social na gestão financeira | G93: https://youtu.be/QQ6HcLQOPeI | H93: ok | I93: finalizado | J93: ok | K93: 2390P013977 | L93: 0.011724537
D94: AULA 15 | E94: Gestão financeira na geração de valor para a empresa: entrevista com Lucy Sousa | G94: https://youtu.be/_CVq9ScSKmU | H94: ok | I94: finalizado | K94: 2390P015449 | L94: 0.012488426
C95: Semana 6 | D95: AULA 16 | E95: Globalização dos mercados e estratégias de internacionalização | G95: https://youtu.be/1SS-xm0GoM0 | H95: ok | I95: finalizado | J95: ok | K95: 2390P013979 | L95: 0.015752315
D96: AULA 17 | E96: Avaliação de oportunidades no mercado global | G96: https://youtu.be/lSqkzlgBBCU | H96: ok | I96: finalizado | J96: ok | K96: 2390P013980 | L96: 0.011956019
D97: AULA 18 | E97: Comércio internacional e as decisões de negócios das empresas: entrevista com Miguel Juan Bacic | G97: https://youtu.be/OqY0qfIEme8 | H97: ok | I97: finalizado | J97: ok | K97: 2390P013981 | L97: 0.012152778
C98: Semana 7 | D98: AULA 19 | E98: Exportação e importação de bens e serviços: procedimentos e requisitos | G98: https://youtu.be/8YhRy_E6rvE | H98: ok | I98: finalizado | J98: ok | K98: 2390P013982 | L98: 0.013252315
D99: AULA 20 | E99: Comércio internacional e questões legais, logísticas e aduaneiras | G99: https://youtu.be/cK1c2BgzBHk | H99: ok | I99: finalizado | J99: ok | K99: 2390P013983 | L99: 0.010914352
D100: AULA 21 | E100: Identificando oportunidades de negócios no mercado global: fatores econômicos, políticos e culturais | G100: https://youtu.be/rViOFIF97V0 | H100: ok | I100: finalizado | J100: ok | K100: 2390P013984 | L100: 0.011828704
A102: ADM380 | B102: =VLOOKUP(A102,Geral!$A$1:$D$36,2,FALSE) -> Gestão de Projetos | C102: Semana 1 | D102: AULA 0 | E102: Apresentação | G102: https://youtu.be/6LiDcv6o6xI | H102: ok | I102: finalizado | J102: ok | K102: 2390P015343 | L102: 0.0024074074 | M102: =VLOOKUP(A102,Geral!$A$1:$D$36,3,FALSE) -> Cíntia Cristina Silva de Araújo | N102: =VLOOKUP(A102,Geral!$A$1:$D$36,4,FALSE) -> Nádia
D103: AULA 01 | E103: O que é um projeto? Conhecendo conceitos básicos | F103: Esta videoaula inicia sua jornada no mundo da gestão de projetos. A videoaula explora o que constitui um projeto, suas características essenciais e como ele se diferencia de processos, programas e portfólios. Além disso, você aprenderá a identificar e aplicar critérios de sucesso em projetos, uma habilidade crucial para avaliar o progresso e os resultados de qualquer empreendimento. Ademais, discutiremos os diferentes tipos de projetos, ajudando você a reconhecê-los e distingui-los com base em suas características específicas. Finalmente, refletiremos sobre a importância de compreender esses conceitos básicos para uma gestão eficaz de projetos no futuro. Esta compreensão é fundamental para qualquer profissional que deseja se destacar na área de gestão de projetos, garantindo que cada etapa do trabalho seja executada com precisão e sucesso. | G103: https://youtu.be/cvZd1ZzbsxU | H103: ok | I103: finalizado | J103: ok | K103: 2390P015344 | L103: 0.016261574
D104: AULA 02 | E104: Gestão do projeto: conhecendo o ciclo de vida e as fases de um projeto | F104: Nesta videoaula, vamos conhecer com detalhes o ciclo de vida de um projeto e explorar suas fases distintas. Assim, você terá uma compreensão conceitual de cada etapa do ciclo de vida de um projeto e sua importância na gestão de projetos. Entender as etapas do ciclo de vida do projeto é essencial para a gestão eficaz de projetos, pois cada uma possui suas próprias atividades, objetivos e entregas específicas. Nesta videoaula, você também aprenderá sobre as atividades e entregas específicas de cada fase do projeto. | G104: https://youtu.be/7Dff1pNo7Fw | H104: ok | I104: finalizado | J104: ok | K104: 2390P015345 | L104: 0.015347222
D105: AULA 03 | E105: Desvendando os papéis-chave e o plano de projeto | F105: Nesta videoaula, você aprenderá sobre as responsabilidades e influências das partes interessadas (stakeholders) em um projeto e aprenderá a identificar esses stakeholders e suas responsabilidades, algo crucial para a gestão eficaz de projetos. Além disso, você aprenderá a elaborar um plano de projeto, definindo objetivos, escopo, recursos e cronograma. Por fim, esta videoaula mostrará como avaliar a eficácia e a viabilidade de um plano de projeto. | G105: https://youtu.be/ZFOG0WplJUQ | H105: ok | I105: finalizado | J105: ok | K105: 2390P015346 | L105: 0.015185185
...

Sheet 2024.4
A1: CÓD | B1: Disciplina | C1: Semanas | D1: Nº de aulas | E1: Título da aula | F1: Sinopse da Videoaula | G1: Link no YouTube | H1: Slide na pasta | I1: Status | J1: Download | K1: ID (TV Cultura) | L1: Duração | M1: Professor | N1: DI
A2: ADM300 | B2: =VLOOKUP(A2,Geral!$A$1:$D$36,2,FALSE) -> Legislação e Responsabilidade Profissional | C2: Semana 1 | D2: AULA 0 | E2: Apresentação | G2: https://youtu.be/Ryp3n8c34uQ | H2: ok | I2: finalizado | J2: ok | K2: 2390P013669 | L2: 0.0011921296 | M2: =VLOOKUP(A2,Geral!$A$1:$D$36,3,FALSE) -> Juliana Novi | N2: =VLOOKUP(A2,Geral!$A$1:$D$36,4,FALSE) -> Fábio
D3: AULA 01 | E3: Direito e Sociologia | G3: https://youtu.be/vyIbsQreoOg | H3: ok | I3: finalizado | J3: ok | K3: 2390P013619 | L3: 0.014386574
C4: Semana 2 | D4: AULA 02 | E4: Implicações jurídicas na vida profissional do engenheiro | F4: e | G4: https://youtu.be/LfiBxsqPyig | H4: ok | I4: finalizado | J4: ok | K4: 2390P015396 | L4: 0.014930556
C5: Semana 3 | D5: AULA 03 | E5: Cidadania e Direitos | G5: https://youtu.be/NcPJ-N-Q_X8 | H5: ok | I5: finalizado | J5: ok | K5: 2390P014598 | L5: 0.013113426
C6: Semana 4 | D6: AULA 04 | E6: Lei Geral de Proteção de Dados | G6: https://youtu.be/eRWQNq6E8SA | H6: ok | I6: finalizado | J6: ok | K6: 2390P013622 | L6: 0.014143519
C7: Semana 5 | D7: AULA 05 | E7: Propriedade Intelectual | G7: https://youtu.be/ZSsudXfl0AQ | H7: ok | I7: finalizado | J7: ok | K7: 2390P013623 | L7: 0.014803241
C8: Semana 6 | D8: AULA 06 | E8: Direito Digital e Internet | G8: https://youtu.be/WZ5qikB7RLo | H8: ok | I8: finalizado | J8: ok | K8: 2390P013621 | L8: 0.01193287
C9: Semana 7 | D9: AULA 07 | E9: Software e Licenças | G9: https://youtu.be/C_H8SvNRNig | H9: ok | I9: finalizado | J9: ok | K9: 2390P013625 | L9: 0.015381944
A11: SEJ001 | B11: =VLOOKUP(A11,Geral!$A$1:$D$36,2,FALSE) -> Educação de Jovens e Adultos | C11: Semana 1 | D11: AULA 0 | E11: Apresentação | G11: https://youtu.be/RBX-fIxKIzc | H11: ok | I11: finalizado | J11: ok | K11: 2390P013788 | L11: =VLOOKUP(A11,Geral!$A$1:$D$36,3,FALSE) -> Adriana Batista de Souza Koide | M11: 0.0034722222 | N11: =VLOOKUP(A11,Geral!$A$1:$D$36,4,FALSE) -> Juliana
D12: AULA 01 | E12: Histórico da educação de jovens e adultos no Brasil | F12: Nesta primeira videoaula, a Profª Adriana Batista de Souza Koide tratará sobre a definição contemporânea da EJA, construída sobre suas memórias históricas, entendendo-a como real espaço de educação formal, com políticas públicas específicas. | G12: https://youtu.be/eXQkTg2yu1E | H12: ok | I12: finalizado | J12: ok | K12: 2390P015382 | M12: 0.0078587963
D13: AULA 02 | E13: Marcos legais e políticas públicas para a Educação de Jovens e Adultos no Brasil | F13: Nesta videoaula, a Profª Adriana Batista de Souza Koide abordará marcos legais e políticas públicas que fundamentam e consolidam a Educação de Jovens e Adultos, destacando que a educação se faz ao longo da vida, em todos os espaços e em todas as relações. | G13: https://youtu.be/oS-NieQXpo0 | H13: ok | I13: finalizado | J13: ok | K13: 2390P015383 | M13: 0.009212963
C14: Semana 2 | D14: AULA 03 | E14: Alfabetização, letramento e cidadania para jovens e adultos | F14: A videoaula tem como objetivo propiciar a identificação do processo de alfabetização na perspectiva do letramento no contexto da Educação de Jovens e Adultos, dialogando com a compreensão de práticas e conceitos sobre como a alfabetização e o letramento estão relacionados à construção do conhecimento e com os impactos da escolarização na vida humana. | G14: https://youtu.be/Jvj7DPb081o | H14: ok | I14: finalizado | J14: ok | K14: 2390P013791 | M14: 0.0078819444
D15: AULA 04 | E15: Alfabetização científica e consciência crítica na educação de jovens e adultos | F15: A videoaula intenta fomentar a reflexão sobre práticas que desenvolvam a alfabetização científica e o letramento crítico nos estudantes adultos, bem como destaca as diferenças entre a consciência ingênua e a consciência crítica, discutindo acerca da relação entre alfabetização, letramento, cidadania e educação a partir das contribuições de Paulo Freire. | G15: https://youtu.be/I1NmnytpXAM | H15: ok | I15: finalizado | J15: ok | K15: 2390P013792 | M15: 0.0084606481
C16: Semana 3 | D16: AULA 05 | E16: Práticas pedagógicas e propostas didáticas para a educação de jovens e adultos | F16: A videoaula tem como objetivo propiciar a análise crítica das práticas e metodologias utilizadas na Educação de Jovens e Adultos, fomentando reflexões sobre a identificação e a aplicação de propostas didáticas adequadas ao público adulto. | G16: https://youtu.be/ZWNDyQO3Urw | H16: ok | I16: finalizado | J16: ok | K16: 2390P013793 | M16: 0.0069560185
D17: AULA 06 | E17: Seleção e análise de materiais e recursos educacionais para a Educação de Jovens e Adultos | F17: O propósito da videoaula está em propiciar reflexões sobre a identificação e possíveis aplicações de propostas didáticas adequadas ao público adulto. | G17: https://youtu.be/GWV0anu1knE | H17: ok | I17: finalizado | J17: ok | K17: 2390P013794 | M17: 0.010150463
D18: AULA 7 | E18: Alfabetização e Paulo Freire | F18: A proposta de reflexão da videoaula trata sobre as contribuições de Paulo Freire para a Educação de Jovens e Adultos, com enfoque sobre a transição de consciência: ingênua e crítica. | G18: https://youtu.be/WAHeVm3OA6g | H18: ok | I18: finalizado | J18: ok | K18: 2390P013795 | M18: 0.0059027778
C19: Semana 4 | D19: AULA 08 | E19: Currículo: propostas disciplinares e diversidade | F19: O foco da videoaula consiste em colocar em diálogo as práticas pedagógicas, a diversidade e o currículo para a Educação de Jovens e Adultos, verificando possibilidades inovadoras e especificidades das manifestações e abordagens do currículo. | G19: https://youtu.be/mi2nl3VEAcY | H19: ok | I19: finalizado | J19: ok | K19: 2390P016297 | M19: 0.0092592593
D20: AULA 09 | E20: Direitos Humanos e Interdisciplinaridade | F20: A videoaula tem como propósito instigar a reflexão sobre temas possivelmente relevantes para a discussão sobre currículo na Educação de Jovens e Adultos, por exemplo: cidadania, trabalho e saúde. A proposta de currículo também é aberta para o respeito à diversidade e aos direitos humanos. | G20: https://youtu.be/BSBcdbSsrAs | H20: ok | I20: finalizado | J20: ok | K20: 2390P013797 | M20: 0.012164352
D21: AULA 10 | E21: As Demandas da Educação de Jovens e Adultos e algumas proposições da Neurociência | F21: Adaptação, flexibilização de currículo é a proposta central da videoaula, com o intuito de atendimento para as diversidades, necessidades e interesses dos estudantes da Educação de Jovens e Adultos, com respaldo em estudos neurocientíficos. Há também a proposta de análise de currículos destinados à EJA na videoaula, com olhar direcionado para adaptações/flexibilizações. | G21: https://youtu.be/RQ0CNg-ve4s | H21: ok | I21: finalizado | J21: ok | K21: 2390P013798 | M21: 0.011643519
C22: Semana 5 | D22: AULA 11 | E22: DIFICULDADES DE APRENDIZAGEM E EDUCAÇÃO INCLUSIVA NA EDUCAÇÃO DE JOVENS E ADULTOS | F22: A videoaula propõe a reflexão sobre a definição de Educação Especial e Educação Inclusiva, abordando dificuldades de aprendizagem e possíveis práticas inclusivas na Educação de Jovens e Adultos. | G22: https://youtu.be/65VNHT6PkRo | H22: ok | I22: finalizado | J22: ok | K22: 2390P013799 | M22: 0.01556713
D23: AULA 12 | E23: Educação de Jovens e Adultos em situação de privação/restrição de liberdade | F23: A videoaula tem como propósito ampliar olhares sobre os possíveis perfis de estudantes da Educação de Jovens e Adultos e de seus contextos sociais e culturais, atentando-se para situações em que ocorrem a privação ou restrição de liberdade, ou seja, trata-se de propor reflexões sobre a escola na prisão. | G23: https://youtu.be/y-VmE4wPoZw | H23: ok | I23: finalizado | J23: ok | K23: 2390P013800 | M23: 0.012766204
D24: AULA 13 | E24: Educação de Jovens e Adultos para quilombolas, indígenas, moradores do campo e itinerantes | F24: A videoaula se dedica a continuar fomentando reflexões sobre os possíveis perfis de estudantes da Educação de Jovens e Adultos e de seus contextos sociais e culturais, voltando a atenção para a pluralidade e a visibilidade dos estudantes de EJA quilombolas, indígenas, moradores do campo e itinerantes. | G24: https://youtu.be/XO8EsahwI2I | H24: ok | I24: finalizado | J24: ok | K24: 2390P013801 | M24: 0.01755787
C25: Semana 6 | D25: AULA 14 | E25: Metodologias ativas e recursos tecnológicos na educação de jovens e adultos | G25: https://youtu.be/1wkRYohT48A | H25: ok | I25: finalizado | J25: ok | K25: 2390P013802 | M25: 0.014525463
D26: AULA 15 | E26: Avaliação na educação de jovens e adultos | G26: https://youtu.be/9_CtO6w78Uc | H26: ok | I26: finalizado | J26: ok | K26: 2390P013803 | M26: 0.014224537
C27: Semana 7 | D27: AULA 16 | E27: Projetos, ações e trocas de experiências | G27: https://youtu.be/vYZs32RQI64 | H27: ok | I27: finalizado | J27: ok | K27: 2390P013804 | M27: 0.0084837963
D28: AULA 17 | E28: A Educação de Jovens e Adultos em Ação | G28: https://youtu.be/EGKARAeSifQ | H28: ok | I28: finalizado | J28: ok | K28: 2390P015441 | M28: 0.010219907
D29: AULA 18 | E29: Formação de professores | G29: https://youtu.be/BfmK_1sWPi4 | I29: finalizado | J29: ok | K29: 2390P015452 | M29: 0.010462963
A31: CIN300 | B31: =VLOOKUP(A31,Geral!$A$1:$D$36,2,FALSE) -> Gestão de Sistemas de Informação | C31: Semana 1 | D31: AULA 0 | E31: Apresentação | G31: https://youtu.be/-vY3zo9m77E | H31: ok | I31: finalizado | J31: ok | K31: 2390P015321 | L31: 0.0016782407 | M31: =VLOOKUP(A31,Geral!$A$1:$D$36,3,FALSE) -> Antonio Francisco Savi | N31: =VLOOKUP(A31,Geral!$A$1:$D$36,4,FALSE) -> Daniel
D32: AULA 01 | E32: Conceitos básicos: dados , informação e o papel nas organizações | G32: https://youtu.be/F9QKJd3ect4 | H32: ok | I32: finalizado | J32: ok | K32: 2390P015322 | L32: 0.0082986111
D33: AULA 02 | E33: Definição e contruibuição dos sistemas de informação na gestão organizacional | G33: https://youtu.be/PNG0GLqaNPU | H33: ok | I33: finalizado | J33: ok | K33: 2390P015323 | L33: 0.012650463
D34: AULA 03 | E34: Tecnologias da informação e comunicação (TIC) nos sistemas de informação empresariais | G34: https://youtu.be/AqsiIuHEq-Q | H34: ok | I34: finalizado | J34: ok | K34: 2390P015324 | L34: 0.0087037037
C35: Semana 2 | D35: AULA 04 | E35: Sistemas de informação: identificando suas cinco áreas de conhecimento | G35: https://youtu.be/hgKN8EsZyhM | H35: ok | I35: finalizado | J35: ok | K35: 2390P015325 | L35: 0.010069444
D36: AULA 05 | E36: Tecnologias utilizadas em sistemas de informação empresariais | G36: https://youtu.be/rSDu9psovvA | H36: ok | I36: finalizado | J36: ok | K36: 2390P015326 | L36: 0.015115741
D37: AULA 06 | E37: Sistemas ERP (Enterprise Resourse Planning), SIG (sistemas de Informação Gerencial) e e-commerce | G37: https://youtu.be/8HyHD5CZews | H37: ok | I37: finalizado | J37: ok | K37: 2390P015327 | L37: 0.0085648148
C38: Semana 3 | D38: AULA 07 | E38: O papel dos sistemas de informação nas decisões empresariais | G38: https://youtu.be/7H3P9hjaaag | H38: ok | I38: finalizado | J38: ok | K38: 2390P015328 | L38: 0.0097800926
D39: AULA 08 | E39: Classificação dos sistemas de informação | G39: https://youtu.be/SEuo-OZ9HjY | H39: ok | I39: finalizado | J39: ok | K39: 2390P015329 | L39: 0.0089467593
D40: AULA 09 | E40: E-commerce nas estratégias de negócios e na gestão da cadeia de suprimentos | G40: https://youtu.be/dno20kR3vy4 | H40: ok | I40: finalizado | J40: ok | K40: 2390P015330 | L40: 0.010509259
C41: Semana 4 | D41: AULA 10 | E41: Gestão de Sistemas Seguros | G41: https://youtu.be/Sk9kAy_yjh0 | H41: ok | I41: finalizado | J41: ok | K41: 2390P015331 | L41: 0.008900463
D42: AULA 11 | E42: Segurança em várias camadas | G42: https://youtu.be/OM8SQu4TQJE | H42: ok | I42: finalizado | J42: ok | K42: 2390P015333 | L42: 0.0085532407
D43: AULA 12 | E43: Práticas para mitigar as ameaças a segurança | G43: https://youtu.be/DhWAf3OHAtM | H43: ok | I43: finalizado | J43: ok | K43: 2390P015332 | L43: 0.0074652778
C44: Semana 5 | D44: AULA 13 | E44: Extended Enterprise: conceitos | G44: https://youtu.be/urNzdhVwQcQ | H44: ok | I44: finalizado | J44: ok | K44: 2390P015334 | L44: 0.0075694444
D45: AULA 14 | E45: Supply Chain e extended enterprise | G45: https://youtu.be/_9uVQwn7PZM | H45: ok | I45: finalizado | J45: ok | K45: 2390P015335 | L45: 0.0079166667
D46: AULA 15 | E46: ERP e extended enterprise | G46: https://youtu.be/yITmFAL5pm4 | H46: ok | I46: finalizado | J46: ok | K46: 2390P015336 | L46: 0.0096412037
C47: Semana 6 | D47: AULA 16 | E47: Conceito de processos | G47: https://youtu.be/qnU4p2XYTnY | H47: ok | I47: finalizado | J47: ok | K47: 2390P015337 | L47: 0.010150463
D48: AULA 17 | E48: Ferramentas e técnicas utilizadas para o gerenciamento de processos | G48: https://youtu.be/lvsHZWD_SFw | H48: ok | I48: finalizado | J48: ok | K48: 2390P015338 | L48: 0.0089814815
D49: AULA 18 | E49: Sistemas de informação como ferramenta de melhoria de processo | G49: https://youtu.be/pNjnHr9kV6E | H49: ok | I49: finalizado | J49: ok | K49: 2390P015339 | L49: 0.011030093
C50: Semana 7 | D50: AULA 19 | E50: Desenvolvimento e uso de sistemas de informação | G50: https://youtu.be/m6Amm1kjo6o | H50: ok | I50: finalizado | J50: ok | K50: 2390P015340 | L50: 0.0070833333
D51: AULA 20 | E51: Resolução de problemas com sistemas de informação | G51: https://youtu.be/HDBRzDV6SAY | H51: ok | I51: finalizado | J51: ok | K51: 2390P015341 | L51: 0.0068981481
D52: AULA 21 | E52: Sistemas de negócios eletrônicios e sistemas de apoio a decisão | G52: https://youtu.be/kpKoYUbnhOE | H52: ok | I52: finalizado | J52: ok | K52: 2390P015342 | L52: 0.0073148148
A54: ADM370 | B54: =VLOOKUP(A54,Geral!$A$1:$D$36,2,FALSE) -> Marketing Digital | C54: Semana 1 | D54: AULA 0 | E54: Apresentação | G54: https://youtu.be/sfPMqly96f4 | H54: ok | I54: finalizado | J54: ok | K54: 2390P014315 | L54: 0.0010300926 | M54: =VLOOKUP(A54,Geral!$A$1:$D$36,3,FALSE) -> Marina Toledo Lourenção Rocha | N54: =VLOOKUP(A54,Geral!$A$1:$D$36,4,FALSE) -> Fábia
D55: AULA 01 | E55: Tendências fundamentais: moldando o marketing digital | G55: https://youtu.be/KlQLQ3i32jA | H55: ok | I55: finalizado | J55: ok | K55: 2390P014316 | L55: 0.01287037
D56: AULA 02 | E56: Consequências da mudança e o novo caminho do consumidor | G56: https://youtu.be/YNPE-qcES3w | H56: ok | I56: finalizado | J56: ok | K56: 2390P014317 | L56: 0.012349537
D57: AULA 03 | E57: Marketing omnichannel: compromisso com a marca | G57: https://youtu.be/wZY8SuHna9U | H57: ok | I57: finalizado | J57: ok | K57: 2390P014318 | L57: 0.014097222
C58: Semana 2 | D58: AULA 04 | E58: O que é estratégia digital | G58: https://youtu.be/ONWkXZCMgDg | H58: ok | I58: finalizado | J58: ok | K58: 2390P014319 | L58: 0.014444444
D59: AULA 05 | E59: Desenvolvimento de planejamento estratégico digital | G59: https://youtu.be/8Wd9GAcCaSs | H59: ok | I59: finalizado | J59: ok | K59: 2390P014320 | L59: 0.0097569444
D60: AULA 06 | E60: Estudo sobre os mecanismos de busca na internet, incluindo SEO e SEM | G60: https://youtu.be/uwk_lZWa8no | I60: finalizado | J60: ok | K60: 2390P014321 | L60: 0.014016204
C61: Semana 3 | D61: AULA 07 | E61: Como definir a persona da minha marca? | G61: https://youtu.be/pW-ZsURnh10 | H61: ok | I61: finalizado | J61: ok | K61: 2390P014322 | L61: 0.015486111
D62: AULA 08 | E62: Estratégias de marketing digital: criação de landing page e ações crossmedia | G62: https://youtu.be/iw3CUySM9n8 | H62: ok | I62: finalizado | J62: ok | K62: 2390P014323 | L62: 0.0068055556
D63: AULA 09 | E63: Planejamento de palavras-chave | G63: https://youtu.be/MP-wufcUujg | H63: ok | I63: finalizado | J63: ok | K63: 2390P014324 | L63: 0.011377315
C64: Semana 4 | D64: AULA 10 | E64: Inbound marketing e planejamento de conteúdo | G64: https://youtu.be/WOXYoT1xFO8 | H64: ok | I64: finalizado | J64: ok | K64: 2390P014325 | L64: 0.010729167
D65: AULA 11 | E65: Blogs e sites, e-mail marketing | G65: https://youtu.be/sFQN95xYKy8 | H65: ok | I65: finalizado | J65: ok | K65: 2390P014326 | L65: 0.014872685
D66: AULA 12 | E66: Anúncio em redes sociais | G66: https://youtu.be/XFTBsz_4kGc | H66: ok | I66: finalizado | J66: ok | K66: 2390P014327 | L66: 0.012291667
C67: Semana 5 | D67: AULA 13 | E67: Funções do social media, analista de marketing digital e níveis hierárquicos | G67: https://youtu.be/RLW-IQP1uSc | H67: ok | I67: finalizado | J67: ok | K67: 2390P014328 | L67: 0.0095717593
D68: AULA 14 | E68: Branding digital: relacionamento, experiência, humanização e engajamento | G68: https://youtu.be/YkgrcqOBMIY | H68: ok | I68: finalizado | J68: ok | K68: 2390P014329 | L68: 0.013564815
D69: AULA 15 | E69: M-commerce, mobile marketing, aplicativos e tendências | G69: https://youtu.be/DnuHFrBch8M | H69: ok | I69: finalizado | J69: ok | K69: 2390P014330 | L69: 0.0096990741
C70: Semana 6 | D70: AULA 16 | E70: Conhecimento das melhores práticas relacionadas à LGPD e privacidade | G70: https://youtu.be/ZnXspO4ylh4 | I70: finalizado | J70: ok | K70: 2390P014331 | L70: 0.0054050926
D71: AULA 17 | E71: Exploração das tecnologias de monitoramento da jornada do usuário | G71: https://youtu.be/RBTterLVEeY | H71: ok | I71: finalizado | J71: ok | K71: 2390P014332 | L71: 0.012824074
D72: AULA 18 | E72: Compreensão das ferramentas e plataformas de automação de marketing | G72: https://youtu.be/T8xxh2mae5g | H72: ok | I72: finalizado | J72: ok | K72: 2390P014333 | L72: 0.0097800926
C73: Semana 7 | D73: AULA 19 | E73: Definição de metas e indicadores de desempenho (KPIs) para medir o sucesso das estratégias | G73: https://youtu.be/jOkc4dz3jeI | I73: finalizado | J73: ok | K73: 2390P014334 | L73: 0.013194444
D74: AULA 20 | E74: Métricas em redes sociais, ferramentas Google e em sites | G74: https://youtu.be/k4KoN-DyXgE | H74: ok | I74: finalizado | J74: ok | K74: 2390P014335 | L74: 0.0070833333
D75: AULA 21 | E75: Tomada de decisão: análise das métricas | G75: https://youtu.be/T4C6OZvJC6E | H75: ok | I75: finalizado | J75: ok | K75: 2390P014336 | L75: 0.007974537
A77: EPR310 | B77: =VLOOKUP(A77,Geral!$A$1:$D$36,2,FALSE) -> Pesquisa Operacional II | C77: Semana 1 | D77: AULA 0 | E77: Apresentação | G77: https://youtu.be/bqyICKPmOeI | H77: ok | I77: finalizado | J77: ok | K77: 2390P015398 | L77: 0.0021180556 | M77: =VLOOKUP(A77,Geral!$A$1:$D$36,3,FALSE) -> Anibal Tavares De Azevedo | N77: =VLOOKUP(A77,Geral!$A$1:$D$36,4,FALSE) -> Ieda
D78: AULA 01 | E78: Ciência de dados + PO - Entrevista com Catarina Junqueira | G78: https://youtu.be/9_RQt9oWdsU | H78: ok | I78: finalizado | J78: ok | K78: 2390P015399 | L78: 0.014490741
D79: AULA 02 | E79: Habilidades e Ferramentas | G79: https://youtu.be/3nTV9ynHnNk | H79: ok | I79: finalizado | J79: ok | K79: 2390P015400 | L79: 0.014768519
D80: AULA 03 | E80: Planejamento de Produção | G80: https://youtu.be/ltCdkGh3X-E | H80: ok | I80: finalizado | J80: ok | K80: 2390P015401 | L80: 0.013900463
C81: Semana 2 | D81: AULA 04 | E81: Você consultor em Pesquisa Operacional | G81: https://youtu.be/zl8Rk_7L0KE | H81: ok | I81: finalizado | J81: ok | K81: 2390P015402 | L81: 0.014016204
D82: AULA 05 | E82: Escala de Funcionários - Teoria | G82: https://youtu.be/svo9jhwHSvY | H82: ok | I82: finalizado | J82: ok | K82: 2390P015403 | L82: 0.012395833
D83: AULA 06 | E83: Escala de Funcionários - Python | G83: https://youtu.be/L09by-cxnIE | H83: ok | I83: finalizado | J83: ok | K83: 2390P015404 | L83: 0.014560185
C84: Semana 3 | D84: AULA 07 | E84: Hidrelétricas turbinadas - Entrevista com Dr. Takaaki Ohishi | G84: https://youtu.be/Xf203Nsil_E | H84: ok | I84: finalizado | J84: ok | K84: 2390P015405 | L84: 0.015462963
D85: AULA 08 | E85: Localização de Facilidades - Teoria | G85: https://youtu.be/Bl8HFQcuxoI | H85: ok | I85: finalizado | J85: ok | K85: 2390P015406 | L85: 0.012962963
D86: AULA 09 | E86: Localização de Facilidades - Python | G86: https://youtu.be/fx7R1PJDZwA | H86: ok | I86: finalizado | J86: ok | K86: 2390P015407 | L86: 0.0140625
C87: Semana 4 | D87: AULA 10 | E87: A maior máquina do Brasil - Entrevista com Dr. Secundino Soares Filho | G87: https://youtu.be/VJ3DD5oTUd4 | H87: ok | I87: finalizado | J87: ok | K87: 2390P015408 | L87: 0.015555556
D88: AULA 11 | E88: Caixeiro Viajante e Roteamento de Veículos - Teoria | G88: https://youtu.be/kYxUaizq8-o | H88: ok | I88: finalizado | J88: ok | K88: 2390P015409 | L88: 0.0098842593
D89: AULA 12 | E89: Caixeiro Viajante e Roteamento de Veículos - Python | G89: https://youtu.be/clh66ua5PkI | H89: ok | I89: finalizado | J89: ok | K89: 2390P015410 | L89: 0.010150463
C90: Semana 5 | D90: AULA 13 | E90: Lean e Pesquisa Operacional em CDs Entrevista com Marcos Schroeder | G90: https://youtu.be/zTceCQe6JUs | H90: ok | I90: finalizado | J90: ok | K90: 2390P015411 | L90: 0.013738426
D91: AULA 14 | E91: Sequenciamento de Tarefas – Teoria | G91: https://youtu.be/UjYfiE7Xeww | H91: ok | I91: finalizado | J91: ok | K91: 2390P015412 | L91: 0.013726852
D92: AULA 15 | E92: Sequenciamento de Tarefas - Python | G92: https://youtu.be/vjt3nJ7Iw20 | H92: ok | I92: finalizado | J92: ok | K92: 2390P015413 | L92: 0.01193287
C93: Semana 6 | D93: AULA 16 | E93: Gêmeo digital industrial - Entrevista com Michael Machado | G93: https://youtu.be/I9q9ig8yzMQ | H93: ok | I93: finalizado | J93: ok | K93: 2390P016335 | L93: 0.014849537
D94: AULA 17 | E94: Corte e empacotamento - Teoria | G94: https://youtu.be/LSYNpumVsLk | H94: ok | I94: finalizado | J94: ok | K94: 2390P015415 | L94: 0.01380787
D95: AULA 18 | E95: Corte e empacotamento - Python | G95: https://youtu.be/R_Upmg7C8-0 | H95: ok | I95: finalizado | J95: ok | K95: 2390P015416 | L95: 0.012152778
C96: Semana 7 | D96: AULA 19 | E96: Logística avançada no varejo Entrevista com Bernardo Almada-Lobo | G96: https://youtu.be/46hO-JlDx98 | H96: ok | I96: finalizado | J96: ok | K96: 2390P015417 | L96: 0.015034722
D97: AULA 20 | E97: Pesquisa Operacional na ATT e na Amazon – Entrevista com Maurício Resende | G97: https://youtu.be/fhJbsdLJepo | H97: ok | I97: finalizado | J97: ok | K97: 2390P015418 | L97: 0.01306713
D98: AULA 21 | E98: Integração e Perspectivas | G98: https://youtu.be/AchajPhKuQc | H98: ok | I98: finalizado | J98: ok | K98: 2390P015419 | L98: 0.012719907
A100: ADM360 | B100: =VLOOKUP(A100,Geral!$A$1:$D$36,2,FALSE) -> Análise e modelagem de processos | C100: Semana 1 | D100: AULA 0 | E100: Apresentação | G100: https://youtu.be/EdVpjYWVb3g | H100: ok | I100: finalizado | J100: ok | K100: 2390P015270 | L100: 0.0018055556 | M100: =VLOOKUP(A100,Geral!$A$1:$D$36,3,FALSE) -> Renato da Costa dos Santos | N100: =VLOOKUP(A100,Geral!$A$1:$D$36,4,FALSE) -> Joel
D101: AULA 01 | E101: Conceitos e objetivos da gestão de processos de negócio | G101: https://youtu.be/5h_KxtotPa4 | H101: ok | I101: finalizado | J101: ok | K101: 2390P015249 | L101: 0.011122685
D102: AULA 02 | E102: Objetivos e benefícios da gestão de processos | G102: https://youtu.be/sBWz-vZsBf8 | H102: ok | I102: finalizado | J102: ok | K102: 2390P015250 | L102: 0.012847222
D103: AULA 03 | E103: Conceitos-chave relacionados à gestão de processos de negócio | G103: https://youtu.be/jcSPwQK8YvQ | H103: ok | I103: finalizado | J103: ok | K103: 2390P015251 | L103: 0.012199074
C104: Semana 2 | D104: AULA 04 | E104: Identificar, analisar e representar processos de negócio | G104: https://youtu.be/4kJOOGb0_OU | H104: ok | I104: finalizado | J104: ok | K104: 2390P015252 | L104: 0.012881944
D105: AULA 05 | E105: Técnicas e metodologias utilizadas na modelagem de processos | G105: https://youtu.be/DJ5yUjhkfN4 | H105: ok | I105: finalizado | J105: ok | K105: 2390P015253 | L105: 0.010601852
...

Sheet Acessibilidade
G1: TV ACESSIBILIDADE | J1: MONTAGEM
A2: Código | B2: Disciplina | C2: Semana | D2: N° de aulas | E2: Título | F2: Link Original | G2: Link Libras | H2: Link Audiodescrição | I2: Legendas REVISADAS | J2: Foi inserido no ava? | K2: Conteudista | L2: Bim
A3: FIS300 | B3: =VLOOKUP(A3,Geral!$A$1:$D$43,2,FALSE) -> Física do Movimento (Engenharia de Computação 2020.1) | C3: Semana 1 | D3: AULA 01 | E3: Tempo e relógio atômico | F3: https://youtu.be/xfvYYbW9GEo | H3: https://youtu.be/SZZnYoplAQQ | I3: ok | J3: ok | L3: =VLOOKUP(A3,Geral!A:G,7,0) -> 2024.2 AC
D4: AULA 02 | E4: Espaço, Tempo e matéria - Referências e Coordenadas | F4: https://youtu.be/vhr56G8ZtuU | H4: https://youtu.be/pOk5GaXOufM | I4: ok | J4: ok
D5: AULA 03 | E5: Algarismos significativos e Incertezas - Exercícios | F5: https://youtu.be/IMMMMnZHhOE | H5: https://youtu.be/UtMleuWiH38 | I5: ok | J5: ok
C6: Semana 2 | D6: AULA 04 | E6: Conceitos de cinemática - Parte 1 | F6: https://youtu.be/1OLBTHDqWIE | H6: https://youtu.be/zOwdV125Opg | I6: ok | J6: ok
D7: AULA 05 | E7: Conceitos de cinemática - Parte 2 | F7: https://youtu.be/XKZQotDgj64 | H7: https://youtu.be/XxHS3jneAOc | I7: ok | J7: ok
D8: AULA 06 | E8: Conceitos de cinemática - Parte 3 | F8: https://youtu.be/pZcxF2a2-qs | H8: https://youtu.be/vACNJ5yrXi0 | I8: ok | J8: ok
C9: Semana 3 | D9: AULA 07 | E9: Forças, Newton e Dinâmica | F9: https://youtu.be/2QC5iCTR8z0 | H9: https://youtu.be/qgTzmDkSAvg | I9: ok | J9: ok
D10: AULA 08 | E10: Forças | F10: https://youtu.be/GcVyR_GB1GY | H10: https://youtu.be/O0IQBqg-IfY | I10: ok | J10: ok
D11: AULA 09 | E11: Leis de Newton | F11: https://youtu.be/1fT1nVfbW-4 | H11: https://youtu.be/zIQLfrJQcBw | I11: ok | J11: ok
C12: Semana 4 | D12: AULA 10 | E12: Energia e transformação de Energia | F12: https://youtu.be/kSpLKZaW0XQ | H12: https://youtu.be/QF01omZuWkA | I12: ok | J12: ok
D13: AULA 11 | E13: Energia | F13: https://youtu.be/knhR38J1kOc | H13: https://youtu.be/dHERTiEkYes | I13: ok | J13: ok
D14: AULA 12 | E14: Energia, Potência e Conservação da Energia | F14: https://youtu.be/uqI_SgYWBYs | H14: https://youtu.be/jQH6o6PyynI | I14: ok | J14: ok
C15: Semana 5 | D15: AULA 13 | E15: Sistemas de partículas e colisões | F15: https://youtu.be/cHDO0BYTWO0 | H15: https://youtu.be/U5kalb0Mc14 | I15: ok | J15: ok
D16: AULA 14 | E16: Conservação do momento linear | F16: https://youtu.be/wiY1gEgx5x0 | H16: https://youtu.be/ec_Gyml_Emk | I16: ok | J16: ok
D17: AULA 15 | E17: Sistemas de partículas e colisões - Exemplos | F17: https://youtu.be/UgnDsZFU8Ys | H17: https://youtu.be/yz007Fxx3ts | I17: ok | J17: ok
C18: Semana 6 | D18: AULA 16 | E18: Equilíbrio | F18: https://youtu.be/n80xhVGCe1g | H18: https://youtu.be/WNWkud-yHTk | I18: ok | J18: ok
D19: AULA 17 | E19: Estruturas indeterminadas | F19: https://youtu.be/NX25B_t3FjU | H19: https://youtu.be/sxZ4Rs9Wntc | I19: ok | J19: ok
D20: AULA 18 | E20: Casos especiais | F20: https://youtu.be/EDbHjw1VbcI | H20: https://youtu.be/L0XhNOlsOkM | I20: ok | J20: ok
C21: Semana 7 | D21: AULA 19 | E21: Astronomia e Gravitação Universal | F21: https://youtu.be/7L8GfjQmRAo | H21: https://youtu.be/jgsMR7p7JoE | I21: ok | J21: ok
D22: AULA 20 | E22: Gravitação | F22: https://youtu.be/AHjQLFmXPJc | H22: https://youtu.be/N7AMgXzmkbU | I22: ok | J22: ok
D23: AULA 21 | E23: Leis de Kepler | F23: https://youtu.be/Zp1eKN0a4S4 | H23: https://youtu.be/VkmD1KdrsiQ | I23: ok | J23: ok
A25: MMB002 | B25: =VLOOKUP(A25,Geral!$A$1:$D$50,2,FALSE) -> Matemática básica | C25: Semana 1 | D25: Costurando 1 | E25: Costurando - Semana 1 | F25: https://youtu.be/D8-PdKrR-D8 | G25: https://youtu.be/DIHlOzOvEu8 | H25: https://youtu.be/Fbpwjz96iSQ | I25: ok | J25: ok | K25: =VLOOKUP(A25,Geral!$A$1:$D$50,3,FALSE) -> Prof.Rúbia Barcelos Amaral | L25: =VLOOKUP(A25,Geral!A:G,7,0) -> 2024.2 AC
D26: AULA 01 | E26: Perspectiva histórica da construção dos números e da teoria dos conjuntos | F26: https://youtu.be/iFW8gm-zoR4 | G26: https://youtu.be/2oTRIPxK2PE | H26: https://youtu.be/6_36XTd4WdU | I26: ok | J26: ok
D27: AULA 02 | E27: Noções iniciais de Conjuntos – Parte 1 | F27: https://youtu.be/yzpiMJW3CzM | G27: https://youtu.be/r2oXE6wnv3c | H27: https://youtu.be/YpEZQK_y-P4 | I27: ok | J27: ok
D28: AULA 03 | E28: Noções iniciais de Conjuntos – Parte 2 | F28: https://youtu.be/8O5K-bQQ97o | G28: https://youtu.be/2WjQIfth1iw | H28: https://youtu.be/j4VbGlaUP-o | I28: ok | J28: ok
D29: Costurando 2 | E29: Costurando - Semana 2 | F29: https://youtu.be/1rq2pdPpdmI | G29: https://youtu.be/jt8QmHb4sxI | H29: https://youtu.be/7E1UWUz4PFA | I29: ok | J29: ok
C30: Semana 2 | D30: AULA 04 | E30: Noções de Lógica | F30: https://youtu.be/I9npqB-KkSE | G30: https://youtu.be/wozD-nY2ITI | H30: https://youtu.be/MFc5mbaNtw4 | I30: ok | J30: ok
D31: AULA 05 | E31: Conjuntos numéricos – parte 1 | F31: https://youtu.be/F0c9YLIq5dU | G31: https://youtu.be/A1VO9af4rxA | H31: https://youtu.be/CsCz9-i58s8 | I31: ok | J31: ok
D32: AULA 06 | E32: Conjuntos numéricos – parte 2 | F32: https://youtu.be/VWFaoQPaxmk | G32: https://youtu.be/26zpa9b46-A | H32: https://youtu.be/undJHG0luf8 | I32: ok | J32: ok
D33: Costurando 3 | E33: Costurando - Semana 3 | F33: https://youtu.be/xdHTggX-OCA | G33: https://youtu.be/7NLioFN6vzM | H33: https://youtu.be/6y1l97oX5vI | I33: ok | J33: ok
C34: Semana 3 | D34: AULA 07 | E34: Divisibilidade | F34: https://youtu.be/gcaL43wVftc | G34: https://youtu.be/pSbMKd3Yv0k | H34: https://youtu.be/72vWt0JKPrY | I34: ok | J34: ok
D35: AULA 08 | E35: Frações | F35: https://youtu.be/HP46l0XzsEM | G35: https://youtu.be/p-uMa0XPQIc | H35: https://youtu.be/GrNFug-Ju28 | I35: ok | J35: ok
D36: Costurando 4 | E36: Costurando - Semana 4 | F36: https://youtu.be/4ZGGSvfMQPQ | G36: https://youtu.be/_nuLbDZO20c | H36: https://youtu.be/IFXHCliZkzg | I36: ok | J36: ok
D37: AULA 09 | E37: Operações com frações | F37: https://youtu.be/Koqt286csj0 | G37: https://youtu.be/ziDgbH5PC1A | H37: https://youtu.be/6uGcTooN5u4 | I37: ok | J37: ok
C38: Semana 4 | D38: AULA 10 | E38: Potenciação e Radiciação | F38: https://youtu.be/CDoENi_jWAY | G38: https://youtu.be/xMKQo5QAzAk | H38: https://youtu.be/Z-HoXmj3AZQ | I38: ok | J38: ok
D39: AULA 11 | E39: Notação científica | F39: https://youtu.be/bDVrHTuVaxM | G39: https://youtu.be/mzEXdwdWM6s | H39: https://youtu.be/0sSHxo6ot5U | I39: ok | J39: ok
D40: Costurando 5 | E40: Costurando - Semana 5 | F40: https://youtu.be/uhrlhquQQjM | G40: https://youtu.be/0scuiEF5dtE | H40: https://youtu.be/r3dCmYxuXLk | I40: ok | J40: ok
D41: AULA 12 | E41: Expressões numéricas | F41: https://youtu.be/n_rZc8IRGHM | G41: https://youtu.be/OtM4zPldSOU | H41: https://youtu.be/8-6M1HsL0Tg
C42: Semana 5 | D42: AULA 13 | E42: Expressões numéricas: exercícios | F42: https://youtu.be/k3FbgsVb6DM | G42: https://youtu.be/CpWQrmtUe48 | H42: https://youtu.be/rxQIqGlHJoo | I42: ok | J42: ok
D43: AULA 14 | E43: Razão e Proporção | F43: https://youtu.be/fmtL8_lkOCM | G43: https://youtu.be/YjPyFHUMxRc | H43: https://youtu.be/iAEzBrtgOVM | I43: ok | J43: ok
D44: AULA 15 | E44: Razão e Proporção - Exercícios | F44: https://youtu.be/EggCD5WZmEI | G44: https://youtu.be/kRzHKilMZ8o | H44: https://youtu.be/aHeuWRRkDI8 | I44: ok | J44: ok
D45: Costurando 6 | E45: Costurando - Semana 6 | F45: https://youtu.be/tejNGd5477g | G45: https://youtu.be/BxvGJ7Fj0Ts | H45: https://youtu.be/6oCfnDFfew0 | I45: ok | J45: ok
C46: Semana 6 | D46: AULA 16 | E46: Grandezas Proporcionais | F46: https://youtu.be/gXU2xZ5sR74 | G46: https://youtu.be/7j5YxgX-wxE | H46: https://youtu.be/GlyuRNCy37A | I46: ok | J46: ok
D47: AULA 17 | E47: Regra de Três | F47: https://youtu.be/LyJDqKXwHK4 | G47: https://youtu.be/7_gtJPblld4 | H47: https://youtu.be/w8o-dyXii8A | I47: ok | J47: ok
D48: Costurando 7 | E48: Costurando - Semana 7 | F48: https://youtu.be/8Tnm2HBv12w | G48: https://youtu.be/ztZHBuqVnaE | H48: https://youtu.be/2Pr5pGdhSsM | I48: ok | J48: ok
D49: AULA 18 | E49: Regra de Três: problemas | F49: https://youtu.be/T-5HSfZGKO0 | G49: https://youtu.be/vdEzQms2Liw | H49: https://youtu.be/ygycCSKz7ds
C50: Semana 7 | D50: AULA 19 | E50: Porcentagem | F50: https://youtu.be/RSs7GY-0Itw | G50: https://youtu.be/w0KQvLcPjw0 | H50: https://youtu.be/i27zek2KvvQ | I50: ok | J50: ok
D51: Costurando 8 | E51: Costurando - Semana 8 | F51: https://youtu.be/TjUW0QCRbqc | G51: https://youtu.be/Pposo6gK2TU | H51: https://youtu.be/3WppwJwFHVc | I51: ok | J51: ok
D52: AULA 20 | E52: Porcentagem: problemas | F52: https://youtu.be/Ot241-L6KbA | G52: https://youtu.be/ceyS_YTfkm0 | H52: https://youtu.be/Q1Y3IlC95qg | I52: ok | J52: ok
D53: AULA 21 | E53: Relações entre porcentagem e regra de três | F53: https://youtu.be/y2CIlCDWAdw | G53: https://youtu.be/R8_NWpR83qE | H53: https://youtu.be/f_UmglLrZSM | I53: ok | J53: ok
A55: EDU310 | B55: =VLOOKUP(A55,Geral!$A$1:$D$50,2,FALSE) -> Letramento em LIBRAS para professores | C55: Semana 1 | D55: AULA 01 | E55: Apresentação | F55: https://youtu.be/rUhLsca4UGY | G55: https://youtu.be/PmcuEtCyScA | H55: https://youtu.be/_p46SBZc4f8 | I55: ok | J55: ok | K55: =VLOOKUP(A55,Geral!$A$1:$D$50,3,FALSE) -> Karina Soledad Maldonado Molina | L55: =VLOOKUP(A55,Geral!A:G,7,0) -> 2024.3 AC
D56: AULA 02 | E56: Abordagens da educação de surdos | F56: https://youtu.be/6ZKi1TborVg | G56: https://youtu.be/ZHmElaAAmS8 | H56: https://youtu.be/BcEFyFcVirI | I56: ok | J56: ok
D57: AULA 03 | E57: A educação bilíngue de surdos | F57: https://youtu.be/56K0T80zjOQ | G57: https://youtu.be/KY6g97pcGMI | H57: https://youtu.be/1yK_UXQWrk0 | I57: ok | J57: ok
C58: Semana 2 | D58: Costurando 2 | E58: Semana 2 | F58: https://youtu.be/QeeqTSRLStY | G58: https://youtu.be/vMVNXEr6JXA | H58: https://youtu.be/xNPmh1TMndc | I58: ok | J58: ok
D59: AULA 04 | E59: A Libras como língua | F59: https://youtu.be/UiL18gJRq7k | G59: https://youtu.be/EI6vKaoKdjo | H59: https://youtu.be/xJNt4tPGOiU | I59: ok | J59: ok
D60: AULA 05 | E60: Língua oral auditiva X Língua visual-espacial | F60: https://youtu.be/bEoXtI62BEU | G60: https://youtu.be/kDbsbHcaR_E | H60: https://youtu.be/DGzGQQRrDYs | I60: ok | J60: ok
D61: AULA 06 | E61: Diferentes línguas de sinais | F61: https://youtu.be/dkAszUX3bC4 | G61: https://youtu.be/tA1vgWD15Ts | H61: https://youtu.be/K48tuhMSbSk | I61: ok | J61: ok
C62: Semana 3 | D62: Costurando 3 | E62: Semana 3 | F62: https://youtu.be/bgqItnu9aF8 | G62: https://youtu.be/7lNMHKU4PdI | H62: https://youtu.be/owKfhD4Qxjc | I62: ok | J62: ok
D63: AULA 07 | E63: Estudantes surdos em famílias ouvintes | F63: https://youtu.be/I1PdweOpHj4 | G63: https://youtu.be/uFZvFJiez0c | H63: https://youtu.be/DYB1hSYE_sg | I63: ok | J63: ok
D64: AULA 08 | E64: Libras como língua natural | F64: https://youtu.be/4X0Q72gNVsk | G64: https://youtu.be/5fgBkq6W5Y8 | H64: https://youtu.be/uYH1yI-9kQ8 | I64: ok | J64: ok
D65: AULA 09 | E65: Cultura Surda: aprendizagem da Libras como língua natural | F65: https://youtu.be/Bxu0SV52KAs | G65: https://youtu.be/lra8zPRrv20 | H65: https://youtu.be/R66OoqwVV9I | I65: ok | J65: ok
C66: Semana 4 | D66: Costurando 4 | E66: Semana 4 | F66: https://youtu.be/Vcwfga4A17M | G66: https://youtu.be/EsCshoZWZ8s | H66: https://youtu.be/ic0KS0wgB4s | I66: ok | J66: ok
D67: AULA 10 | E67: A relação pensamento e sinal | F67: https://youtu.be/kQ7mE5d39UQ | G67: https://youtu.be/fsJcVbDpAOE | H67: https://youtu.be/pwf84732EIQ | I67: ok | J67: ok
D68: AULA 11 | E68: Formação de conceitos cotidianos | F68: https://youtu.be/j4TPE6ZV4nw | G68: https://youtu.be/Tx0bsvD5yJg | H68: https://youtu.be/N2ofOSCBw7g | I68: ok | J68: ok
D69: AULA 12 | E69: Formação de conceitos científicos | F69: https://youtu.be/8ozOKLt9jns | G69: https://youtu.be/qnN4eN0ZEXw | H69: https://youtu.be/jEX7a7oMnVI | I69: ok | J69: ok
C70: Semana 5 | D70: Costurando 5 | E70: Semana 5 | F70: https://youtu.be/n7V0hGj2oww | G70: https://youtu.be/aKgL7_FxHd0 | H70: https://youtu.be/TFNqFqL6mpw | I70: ok | J70: ok
D71: AULA 13 | E71: A escolarização de estudantes surdos | F71: https://youtu.be/yMwbubUlmgM | G71: https://youtu.be/ryLa0Z2v6aw | H71: https://youtu.be/td43TqnUDts | I71: ok | J71: ok
D72: AULA 14 | E72: Desconstruindo mitos | F72: https://youtu.be/S9EcaMVmphg | G72: https://youtu.be/HPPOkaDs2lA | H72: https://youtu.be/JG1WXTuM_TA | I72: ok | J72: ok
D73: AULA 15 | E73: Avanços na escolarização de estudantes surdos | F73: https://youtu.be/mqlxbD7jEcg | G73: https://youtu.be/CEoGnv7J500 | H73: https://youtu.be/6A4c0YofrrI | I73: ok | J73: ok
C74: Semana 6 | D74: Costurando 6 | E74: Semana 6 | F74: https://youtu.be/c4EAxiUJUow | G74: https://youtu.be/3kuyUNfIcjU | H74: https://youtu.be/PYJHce9r2AA | I74: ok | J74: ok
D75: AULA 16 | E75: Ensino da LIBRAS como L1 | F75: https://youtu.be/_9UNaPqwEgQ | G75: https://youtu.be/TXqAig39h68 | H75: https://youtu.be/36EWnhPrnO0 | I75: ok | J75: ok
D76: AULA 17 | E76: Libras como língua de instrução | F76: https://youtu.be/yNOOqIk-YCc | G76: https://youtu.be/CaNChuUXOtY | H76: https://youtu.be/82y3yhHTRAs | I76: ok | J76: ok
D77: AULA 18 | E77: Os usos das línguas no espaço escolar bilíngue para surdos | F77: https://youtu.be/-eFyit2BXR8 | G77: https://youtu.be/ayBVNwqY4nc | H77: https://youtu.be/7JFNxWHJYVY | I77: ok | J77: ok
C78: Semana 7 | D78: Costurando 7 | E78: Semana 7 | F78: https://youtu.be/vK9YB-WicmM | G78: https://youtu.be/FPk8aEQwa5g | H78: https://youtu.be/BgDDyE-DQHc | I78: ok | J78: ok
D79: AULA 19 | E79: O ensino da Língua Portuguesa como L2 | F79: https://youtu.be/6ynVUQF3YlU | G79: https://youtu.be/Dz2B1A0sBJg | H79: https://youtu.be/za4pTvjjsRE | I79: ok | J79: ok
D80: AULA 20 | E80: Atividades para o ensino do Português para surdos | F80: https://youtu.be/5qT4xo8dY4Q | G80: https://youtu.be/ZITSU24h2_I | H80: https://youtu.be/PDIQUj5V5GU | I80: ok | J80: ok
D81: AULA 21 | E81: Desafios para o ensino bilíngue para surdos | F81: https://youtu.be/OMdygCJ_4Dc | G81: https://youtu.be/aS1n-GmfeSM | H81: https://youtu.be/oLSGM4pp_e0 | I81: ok | J81: ok
A83: SFI002 | B83: Fundamentos da Educação Infantil II | C83: Semana 1 | D83: AULA 0 | E83: Apresentação | F83: https://youtu.be/JO786bTVnlM | G83: https://youtu.be/Trr20PZol9w | H83: https://youtu.be/iS1MKHfSwpc | I83: ok | J83: ok | K83: =VLOOKUP(A83,Geral!$A$1:$D$50,3,FALSE) -> Claudia Panizzolo | L83: =VLOOKUP(A83,Geral!A:G,7,0) -> 2024.3 AC
D84: AULA 01 | E84: O brincar na educação infantil | F84: https://youtu.be/sLSixZwhZ4A | G84: https://youtu.be/0TDOmr6ggzM | H84: https://youtu.be/q8QTZU23Htk | I84: ok | J84: ok
C85: Semana 2 | D85: AULA 02 | E85: Teorias sobre o desenvolvimento e as experiências de aprendizagem das crianças de 0 a 6 anos | F85: https://youtu.be/kp_siNUY3oY | G85: https://youtu.be/2O-Yqg_mtHg | H85: https://youtu.be/Awf-DbjFLKo | I85: ok | J85: ok
C86: Semana 3 | D86: AULA 03 | E86: Proposta pedagógica: definição, elaboração, implementação e avaliação | F86: https://youtu.be/aitDZifY8hc | G86: https://youtu.be/G7CCtSk4Go0 | H86: https://youtu.be/vZ3jjdhLIRA | I86: ok | J86: ok
C87: Semana 4 | D87: AULA 04 | E87: Organização do trabalho pedagógico: planejamento, observação e registro | F87: https://youtu.be/HdOyNOKxeQY | G87: https://youtu.be/gNujhG6ItAs | H87: https://youtu.be/WxsALQTbros | I87: ok | J87: ok
D88: AULA 05 | E88: Organização do espaço pedagógico: ambientes, espaços e materiais | F88: https://youtu.be/j62DYUW4Dgs | G88: https://youtu.be/d-0SsFOMsRo | H88: https://youtu.be/VrMoa_R--8Y | I88: ok | J88: ok
C89: Semana 5 | D89: AULA 06 | E89: Organização do trabalho pedagógico: tempos, rotina e metodologias de aprendizagem | F89: https://youtu.be/iI0vJ_0b-nE | G89: https://youtu.be/SLBsZQVjdbM | H89: https://youtu.be/SngBJ_PUFgI | I89: ok | J89: ok
D90: AULA 07 | E90: Organização do trabalho pedagógico: instrumentos de avaliação da aprendizagem e do desenvolvimento das crianças e da instituição educacional | F90: https://youtu.be/GW8Y629JkVQ | G90: https://youtu.be/PI7L0JSHfKU | H90: https://youtu.be/je299CED6UM | I90: ok | J90: ok
A92: TPL504 | B92: Projeto Integrador para Licenciatura IV / Letras, Matemática e Pedagogia 2019.1 | C92: Quinzena 1 | E92: A importância das práticas pedagógicas e dos materiais didáticos | F92: https://youtu.be/CMG6j2aiW7A | G92: https://youtu.be/cHLcaiJ9Fqo | H92: https://youtu.be/EZKMTZTDzNk | I92: ok | J92: ok | K92: =VLOOKUP(A92,Geral!$A$1:$D$50,3,FALSE) -> Taitiâny Kárita Bonzanini | L92: =VLOOKUP(A92,Geral!A:G,7,0) -> 2024.3 AC
C93: Quinzena 2 | E93: Educação Inclusiva: práticas pedagógicas e materiais didáticos | F93: https://youtu.be/paNBVR9pab8 | G93: https://youtu.be/M1wKeR4cvF4 | H93: https://youtu.be/IN8EQwJLUbk | I93: ok | J93: ok
C94: Quinzena 3 | E94: Organização do Projeto Integrador: bibliografia, título e proposta | F94: https://youtu.be/LKuthwVnm_Q | G94: https://youtu.be/8e8iGJ_rUhY | H94: https://youtu.be/OfUOngevn8s | I94: ok | J94: ok
C95: Quinzena 4 | E95: Produção de materiais didáticos para a educação inclusiva | F95: https://youtu.be/xLeYUuCmfX0 | G95: https://youtu.be/NMsFeCmrhks | H95: https://youtu.be/KShOja8pFLQ | I95: ok | J95: ok
C96: Quinzena 5 | E96: O projeto proposto e a inclusão: quais características privilegiar? | F96: https://youtu.be/iDI8nf0auTg | G96: https://youtu.be/_d5RYkX41PY | H96: https://youtu.be/t_2Oef_dXtw | I96: ok | J96: ok
C97: Quinzena 6 | E97: Finalizando o projeto integrador: a proposta é inclusiva? | F97: https://youtu.be/dc2mSr0fXjY | G97: https://youtu.be/5ZitX9cUrs8 | H97: https://youtu.be/eehJ9HLB5PM | I97: ok | J97: ok
C98: Quinzena 7 | E98: Entrega do relatório final e vídeo de apresentação do PI | F98: https://youtu.be/jl_urtmEkoU | G98: https://youtu.be/f_EgpOxw4q0 | H98: https://youtu.be/Tlg93XTmS1E | I98: ok | J98: ok
C99: Outros- Quinzena 1 | E99: Revisitando Conhecimentos - Didática para Ciências e Biologia: Introdução às estratégias (1) | F99: https://www.youtube.com/watch?v=YZITfH6XQTc&t=2s | G99: Didática para Ciências e Biologia - Aula 21 - Introdução às estratégias - 1 | H99: https://youtu.be/7XHE5PMZ3EY | K99: Suzana Ursi
C100: Outros- Quinzena 1 | E100: Material Metodológico - Visita a campo | F100: https://www.youtube.com/watch?v=hbwJjlsg4T0&t=567s | G100: https://youtu.be/iXQ54fBOlPk | H100: 1 | K100: Mônica Garbin
C101: Outros- Quinzena 2 | E101: Desafio - Brainstorming | F101: https://www.youtube.com/watch?v=8dLDnRyZyIo&t=6s | G101: https://youtu.be/Ii222F8YKL8 | H101: https://youtu.be/P8FtayEBWa0
C102: Outros- Quinzena 2 | E102: Revisitando Conhecimentos - Avaliação do Projeto Integrador | F102: https://www.youtube.com/watch?v=L4LmgPSnsLk&t=2s | H102: https://youtu.be/ZXjBDtvehA4
C103: Outros- Quinzena 2 | E103: Material Metodológico - Delimitação do tema e desenho do problema | F103: https://www.youtube.com/watch?v=bLB1-aVOHA8&t=2s | G103: https://youtu.be/f_h3Xm5lTdY | H103: https://youtu.be/rim98LsyTbg
C104: Outros- Quinzena 4 | E104: Material Metodológico - Protótipos | F104: https://www.youtube.com/watch?v=2Fu5iSI8LTk&t=18s | G104: https://youtu.be/zWb4FEoulvE | H104: https://youtu.be/nvXTD9JwL10 | I104: ok
...

Sheet COM100 - Marcos
A1: CÓD | B1: Disciplina | C1: Semanas | D1: Nº de aulas | E1: Título da aula | F1: Sinopse da Videoaula | G1: Link no YouTube | H1: Slide na pasta | I1: Status | J1: Download | K1: ID (TV Cultura) | L1: Duração | M1: Professor | N1: DI
C2: Semana 01 | D2: 0 | E2: Bem-Vindos! | G2: https://youtu.be/01Hb_UV-yDA | I2: finalizado | J2: ok | K2: 2390P015450 | L2: 0.011701389
D3: 1 | E3: O Século XXI e a computação na BNCC - Parte 1 | G3: https://youtu.be/GGKLbcpO_DY | H3: OK | I3: finalizado | J3: ok | K3: 2390P015436 | L3: 0.012118056
D4: 2 | E4: O Século XXI e a computação na BNCC - Parte 2 | G4: https://youtu.be/0aPzdqLQezg | H4: OK | I4: finalizado | J4: ok | K4: 2390P015437 | L4: 0.022222222
C5: MATERIAL DE APOIO | E5: Jovem Engenheiro | G5: https://youtu.be/CavGI3hojDs | I5: finalizado | J5: ok | K5: 2390E006221 | L5: 0.0081597222
C6: Semana 02 | D6: 3 | E6: Pensamento Computacional - Parte 1 | G6: https://youtu.be/L-rQmj3xMkI | H6: OK | I6: finalizado | J6: ok | K6: 2390P015438 | L6: 0.017407407
D7: 4 | E7: Pensamento Computacional - Parte 2 | G7: https://youtu.be/Ntq26PHJ-MM | I7: finalizado | J7: ok | K7: 2390P015439 | L7: 0.0077777778
D8: 5 | E8: Pensamento Computacional - Parte 3 | G8: https://youtu.be/4Z5JhJylsic | I8: finalizado | J8: ok | K8: 2390P015440 | L8: 0.0097106481
C9: MATERIAL DE APOIO | E9: A teoria na prática | G9: https://youtu.be/CM-U0bX-0kQ | H9: ( | I9: finalizado | J9: ok
C10: Semana 03 | D10: 6 | E10: Introdução ao Scracth | G10: https://youtu.be/3RW9zEiG6W4 | I10: finalizado | J10: ok | K10: 2390P015453 | L10: 0.0036342593
D11: 7 | E11: Meu primeiro programa | G11: https://youtu.be/fIlciM63TLE | H11: OK | I11: finalizado | J11: ok | K11: 2390P015454 | L11: 0.01412037
D12: 8 | E12: Estruturas de repetição | G12: https://youtu.be/AASk-CP-J88 | H12: OK | I12: finalizado | J12: ok | K12: 2390P015455 | L12: 0.011701389
C13: Semana 04 | D13: 9 | E13: Condicionais - Parte 1 | G13: https://youtu.be/Y9QwlY_GL_M | H13: OK | I13: finalizado | J13: ok | K13: 2390P015456 | L13: 0.01255787
D14: 10 | E14: Condicionais - Parte 2 | G14: https://youtu.be/McVt05VV8lo | I14: finalizado | J14: ok | K14: 2390P015457 | L14: 0.0071180556
D15: 11 | E15: Sons, falas e fantasias | G15: https://youtu.be/RcJoHOw7fbM | H15: OK | I15: finalizado | J15: ok | K15: 2390P015458 | L15: 0.0066203704
D16: 12 | E16: Variáveis | G16: https://youtu.be/Rgf9-jjrhDU | H16: OK | I16: finalizado | J16: ok | K16: 2390P015459 | L16: 0.0066435185
C17: Semana 05 | D17: 13 | E17: Explorando projetos com arte e tecnologia no scracth | G17: https://youtu.be/7e7RgvT5zUw | I17: finalizado | J17: ok | K17: 2390P015460 | L17: 0.010717593
D18: 14 | E18: Remixando projetos no scracth | G18: https://youtu.be/yteOg2jkoV0 | I18: finalizado | J18: ok | K18: 2390P015461
C19: Semana 06 | D19: 15 | E19: Criando projetos autorais | G19: https://youtu.be/Y8Nogbn5ksw | I19: finalizado | J19: ok | K19: 2390P015462 | L19: 0.010277778
D20: 16 | E20: Criando projetos autorais com uso de extensão | G20: https://youtu.be/7gJktl2k97s | I20: finalizado | J20: ok | K20: 2390P015463 | L20: 0.011701389
C21: Semana 07 | D21: 17 | E21: Conteúdo digital e inteligência artificial - Parte 1 | G21: https://youtu.be/HLgWwXI5fWo | H21: OK | I21: finalizado | J21: ok | K21: 2390P015508
D22: 18 | E22: Conteúdo digital e inteligência artificial - Parte 2 | G22: https://youtu.be/17dEbecypfE | H22: OK | I22: finalizado | J22: ok | K22: 2390P015509
D23: 19 | E23: Conteúdo digital e inteligência artificial - Parte 3 | G23: https://youtu.be/CvSbIY4f0GU | H23: OK | I23: finalizado | J23: ok | K23: 2390P015510
D24: 20 | E24: Conteúdo digital e inteligência artificial - Parte 4 | G24: https://youtu.be/S5B31VYLlLA | H24: OK | I24: finalizado | J24: ok | K24: 2390P015511
D25: 21 | E25: Conteúdo digital e inteligência artificial - Parte 5 | G25: https://youtu.be/YFjqnRr00GA | H25: OK | I25: finalizado | J25: ok | K25: 2390P015512
D26: 22 | E26: Conteúdo digital e inteligência artificial - Parte 6 | G26: https://youtu.be/GtFf8ZZYVE4 | H26: OK | I26: finalizado | J26: ok | K26: 2390P015513
D27: 23 | E27: Conteúdo digital e inteligência artificial - Parte 7 | G27: https://youtu.be/-f27KPLQeHs | H27: OK | I27: finalizado | J27: ok | K27: 2390P015514

Sheet Tutorial Univesp 2024
A1: Título da aula | B1: Link no YouTube | C1: ID BRUTO | D1: Duração
A2: Login com E-mail Univesp | B2: https://youtu.be/IBXjbB0yzrA | C2: 2390B013428 | D2: 0.0021643519
A3: E-mail Univesp | B3: https://youtu.be/RhX9z4-pN1E | C3: 2390B013429 | D3: 0.0022222222
A4: Login Teams | B4: https://youtu.be/_G4Bd76P7Dc | C4: 2390B013430 | D4: 0.0023032407
A5: Teams Informativo | B5: https://youtu.be/iaJGjWHId8o | C5: 2390B013431 | D5: 0.0012962963
A6: Teams Tutoriais | B6: https://youtu.be/2fB5eRH3W0o | C6: 2390B013432 | D6: 0.0017476852
A7: Atendimento | B7: https://youtu.be/T3PoVJPss3Y | C7: 2390B013433 | D7: 0.0023263889
A8: Formulários | B8: https://youtu.be/HGK3z-3eVPo | C8: 2390B013434 | D8: 0.0022453704
A9: AVA | B9: https://youtu.be/GIlup20xHLE | C9: 2390B013435 | D9: 0.0031365741
A10: Manual do Aluno | B10: https://youtu.be/YPA623GUF48 | C10: 2390B013436 | D10: 0.0023726852
A11: Atividades das Equipes | B11: https://youtu.be/DfuQpwWk6iE | C11: 2390B013437/2390B013438 | D11: 0.0049884259
A12: Acessos as Plataformas SEI - Provas | B12: https://youtu.be/KiEM9XylOaA | C12: 2390B013460 | D12: 0.0030902778
A13: Bloqueio de Provas | B13: https://youtu.be/8cHORvaq_gc | C13: 2390B013461 | D13: 0.0021296296
... A31: consulta aluno | B31: https://youtu.be/6Dl5-dXFDXk | C31: 2390B013606 | D31: 0.0015625

Sheet Quem Sabe, Ganha!
A1: Episódio | B1: ID YOUTUBE / APP | C1: duração | D1: data postagem | E1: Link no YouTube | F1: Disponivel no app
A2: QUEM SABE, GANHA - 01 - BORBOREMA X VARGEM GRANDE PAULISTA | B2: 3147P000041 | C2: 0.031909722 | D2: 6-jun. | E2: https://youtu.be/7VFatHn2_6M | F2: SIM
A5: QUEM SABE, GANHA - 02 - SERTÃOZINHO X SANTANA DE PARNAÍBA | B5: 3147P000046 | C5: 0.031203704 | D5: 13-jun. | E5: https://youtu.be/7910pqXDncA | F5: SIM
A8: QUEM SABE, GANHA - 03 - GUARUJÁ X SÃO BERNARDO DO CAMPO | B8: 3147P000049 | C8: 0.031701389 | D8: 20-jun. | E8: https://youtu.be/PDvOG5yg9UQ | F8: SIM
A11: QUEM SABE, GANHA - 04 - MIRANTE DO PARANAPANEMA X ITAPECERICA DA SERRA | B11: 3147P000045 | C11: 0.031365741 | D11: 27-jun. | E11: https://youtu.be/sm99pV6zXOY | F11: SIM
A14: QUEM SABE, GANHA - 05 - POÁ X ITAQUAQUECETUBA | B14: 3147P000051 | C14: 0.030729167 | D14: 4-jul. | E14: https://youtu.be/DD57NZJVyX4 | F14: SIM
A17: QUEM SABE, GANHA - 06 - ITÁPOLIS X FRANCA | B17: 3147P000044 | C17: 0.031064815 | D17: 11-jul. | E17: https://youtu.be/oLKdX7vxhMo | F17: SIM
A20: QUEM SABE, GANHA - 07 - IGARAPAVA X CLEMENTINA | B20: 3147P000040 | C20: 0.03099537 | D20: 18-jul. | E20: https://youtu.be/Fzc2aGIAGFs | F20: SIM
A23: QUEM SABE, GANHA - 08 - TUPÃ X POÁ | B23: 3147P000050 | C23: 0.030833333 | D23: 25-jul. | E23: https://youtu.be/d9yq1KVc1vE | F23: SIM
A26: QUEM SABE, GANHA - 09 - CAJURU X SÃO PAULO | B26: 3147P000042 | C26: 0.031215278 | D26: 1-ago. | E26: https://youtu.be/W2Mdy_oox1o | F26: SIM
A29: QUEM SABE, GANHA - 10 - ITAPECERICA DA SERRA X ITAPETININGA | B29: 3147P000048 | C29: 0.03119213 | D29: 8-ago. | E29: https://youtu.be/b2mRlLOrGLY | F29: SIM
A32: QUEM SABE, GANHA - 11 - BARÃO DE ANTONINA X SÃO PAULO | B32: 3147P000043 | C32: 0.031145833 | D32: 15-ago. | E32: https://youtu.be/huNyTWmg78o | F32: SIM
A35: QUEM SABE, GANHA - 12 - OSASCO X SÃO PAULO | B35: 3147P000047 | C35: 0.030972222 | D35: 22-ago. | E35: https://youtu.be/LZ3LVdaBDFg | F35: SIM
A38: QUEM SABE, GANHA - 13 - SÃO JOSÉ DOS CAMPOS X ITAPECERICA DA SERRA | B38: 3147P000052 | C38: 0.030983796 | D38: 29-ago. | E38: https://youtu.be/5QfqzH9OAec | F38: SIM

Sheet Disciplina Paulista de Acessib.
A1: Disciplina | B1: Semanas | C1: Nº de aulas | D1: Título da aula | E1: Sinopse da Videoaula | F1: Link no YouTube | G1: Slide na pasta | H1: Status | I1: Download | J1: ID LIBRAS | K1: Link LIBRAS | L1: Duração | M1: ID AUDIODESCRIÇÃO | N1: Link AD | O1: Professor | P1: DI
A2: Disciplina Paulista de Acessibilidade | C2: 1 | D2: Introdução e Apresentação da Disciplina | G2: ok | J2: 3164P000129 | K2: https://youtu.be/YHjL_xmN7go | L2: 0.67569444 | M2: 3164P000059 | N2: https://youtu.be/E69-DYsTaeM
C3: 2 | D3: Museu da Inclusão | G3: ok | J3: 3164P000121 | K3: https://youtu.be/RrzX_5Vx2IQ | M3: 3164P000060 | N3: https://youtu.be/1CU4Rd9_2lI
C4: 3 | D4: Evolução do Conhecimento da População sobre Deficiência Intelectual (Univesp 2024). | G4: ok | J4: 3164P000102 | K4: https://youtu.be/BcQO8uChjcY | L4: 0.39791667 | M4: 3164P000061 | N4: https://youtu.be/RP3R_Qp9e6I
C5: 4 | D5: Entrevista com Professor Doutor Clodoaldo Meneguello Cardoso | G5: ok | J5: 3164P000130 | K5: https://youtu.be/0XELkbdzp3k | M5: 3164P000062 | N5: https://youtu.be/TWzBDvUeXxY
C6: 5 | D6: Fundamentos históricos legais e concetuais da inclusão | J6: 3164P000104 | K6: https://youtu.be/snq5ipWlj4M | L6: 0.87430556 | M6: 3164P000063 | N6: https://youtu.be/O4HhvFeTIes
C7: 6 | D7: Entrevista com Professora Doutora Carla Biancha Angelucci | J7: 3164P000137 | K7: https://youtu.be/UI_zMgoLByc | M7: 3164P000064 | N7: https://youtu.be/VrVaiYfXPHU
C8: 7 | D8: Deficiência e capacitismo | J8: 3164P000106 | K8: https://youtu.be/BTyL_GXwaV4 | M8: 3164P000065 | N8: https://youtu.be/_ukBwx-M7-Q
C9: 8 | D9: Entrevista com Professor Especialista Ivan de Oliveira Freitas | G9: ok | J9: 3164P000107 | K9: https://youtu.be/T9ccWdju7AQ | M9: 3164P000066 | N9: https://youtu.be/vxd1fGoj5eU
C10: 9 | D10: Entrevista com Professor Doutor Honoris Causa Marcos da Costa, Secretário de Estado dos Direitos da Pessoa com Deficiência. | G10: ok | J10: 3164P000131 | K10: https://youtu.be/imFYu-lUMXY | M10: 3164P000067 | N10: https://youtu.be/5vK8_kUacn8
C11: 10 | D11: Univesp por Elas - Entrevista com Cláudia Carletto | G11: ok | J11: 3164P000122 | K11: https://youtu.be/TB-8CxPeDgE | M11: 3164P000068 | N11: https://youtu.be/bVGpA-9SH-I
C12: 11 | D12: Acessibilidade | G12: ok | J12: 3164P000109 | K12: https://youtu.be/okfKyMM8vm0 | M12: 3164P000069 | N12: https://youtu.be/zK9Mdu5Yfs4
C13: 12 | D13: Videoaula animada: Dimensões da Acessibilidade Parte I | G13: ok | J13: 3164P000024 | K13: https://youtu.be/u3sntETrLQw | M13: 3164P000070 | N13: https://youtu.be/H8BLLgcpNzw
C14: 13 | D14: Videoaula animada: Dimensões da Acessibilidade Parte II | G14: ok | J14: 3164P000026 | K14: https://youtu.be/Cgvj-ujsuiw | M14: 3164P000071 | N14: https://youtu.be/vFB80FG0caE
C15: 14 | D15: Entrevista com Professora Doutora Anna Maria Lunardi Padilha | G15: ok | J15: 3164P000132 | K15: https://youtu.be/mnMio2DM_V8 | M15: 3164P000072 | N15: https://youtu.be/iCC2qKgBcZ0
C16: 15 | D16: Fala Doutor - Cássia Geciauskas Sofiato: Do desenho à litografia - PGM 18 (2012) | G16: ok | J16: 3164P000030 | K16: https://youtu.be/a3gFtcFS8_c | M16: 3164P000073 | N16: https://youtu.be/Mx5V-txH-CA
C17: 16 | D17: Entrevista com Professora Doutora Lígia Rodrigues Balista | G17: ok | J17: 3164P000133 | K17: https://youtu.be/sp0wbwJ2R-U | M17: 3164P000074 | N17: https://youtu.be/E6rMzM-l25E
C18: 17 | D18: Conhecimento da população sobre LIBRAS (2024) | G18: ok | J18: 3164P000124 | K18: https://youtu.be/nPzZ-4E6uBk | M18: 3164P000125 | N18: https://youtu.be/-M_vNKTvfo0
C19: 18 | D19: Tecnologia assistiva | G19: ok | J19: 3164P000113 | K19: https://youtu.be/b36gH-yYGtg | M19: 3164P000076 | N19: https://youtu.be/J3dk4pYSTrg
C20: 19 | D20: D-30 - A tecnologia na Educação Inclusiva | G20: ok | J20: 3164P000038 | K20: https://youtu.be/qunN5PqZblI | M20: 3164P000077 | N20: https://youtu.be/s0BK3eTMQhA
... C26: 25 | D26: Ampliando conhecimentos sobre acessibilidade e inclusão | G26: ok | J26: 3164P000119 | K26: https://youtu.be/Hq4e6t6fhHw | M26: 3164P000083 | N26: https://youtu.be/E54aFmKBKVY
C27: 26 | D27: Entrevista com Professora Mestra Aldine Nogueira da Silva | G27: ok | K27: https://youtu.be/2l76ukmTN0A | M27: 3164P000084 | N27: https://youtu.be/9s5wlJSMQlA
C28: 27 | D28: Entrevista com Professora Doutora Cristina Bressaglia Lucon | G28: ok | J28: 3164P000054 | K28: https://youtu.be/PzT8jxsEtwk | M28: 3164P000085 | N28: https://youtu.be/6R-cnO1WTs8
C29: 28 | D29: Entrevista com Professora Doutora Cícera Aparecida Lima Malheiro | G29: ok | J29: 3164P000136 | K29: https://youtu.be/K6X9yZ6_2QQ | M29: 3164P000086 | N29: https://youtu.be/hHbYDbJ_E5Y
C30: 29 | D30: Eixo Articulador - A Política Nacional para a Educação Inclusiva: Avanços e Desafios | J30: 3164P000088 | K30: https://youtu.be/a2rkyo9zLCk | M30: 3164P000089 | N30: https://youtu.be/kIQcdywRh5U
C31: 30 | D31: Dia Mundial do Braille: deficientes visuais enfrentam dificuldades para educação inclusiva | J31: 3164P000098 | K31: https://youtu.be/Y7auuGCwQWQ | M31: 3164P000099 | N31: https://youtu.be/H5nTzwjSLkE | R31: ???
C32: 31 | D32: Revisão final | G32: ok | J32: 3164P000058 | K32: https://youtu.be/L5VsUNLeZgw | M32: 3164P000087 | N32: https://youtu.be/M3yO2lbOux0

Sheet Planilha1
A1: CÓD. | B1: DISCIPLINA | C1: Semanas | D1: Nº de aulas | E1: Título da aula | F1: Duração | G1: Link Original | H1: Legenda Original | I1: Link LIBRAS | J1: Legenda LIBRAS | K1: Link Audiodescrição | L1: AVA
A2: SCR001 | B2: Teorias do Currículo / Licenciaturas 2019.2 (Prof.Marcos Garcia Neira) | C2: Semana 1 | D2: AULA 01 | E2: Apresentação do curso | F2: 0.006875 | G2: https://youtu.be/xjytbB7IAW8 | H2: finalizado | I2: https://youtu.be/w6QIK30X8SM | J2: finalizado | K2: https://youtu.be/2FgBvOXC4ow
D3: AULA 02 | E3: Currículo: história e concepções | F3: 0.013113426 | G3: https://youtu.be/YWys2JtHYrs | H3: finalizado | I3: https://youtu.be/4Gum-AvzeZo | J3: finalizado | K3: https://youtu.be/6FbjyEHQk3Y
D4: AULA 03 | E4: Teorias tradicionais do currículo: Pedagogia Tradicional | F4: 0.0093981481 | G4: https://youtu.be/S2EJaCn4kI8 | H4: finalizado | I4: https://youtu.be/lXGWLVCZ5nk | J4: finalizado | K4: https://youtu.be/iP-iCxOWVSY
C5: Semana 2 | D5: AULA 04 | E5: Teorias tradicionais do currículo: escolanovismo | F5: 0.011041667 | G5: https://youtu.be/-J2YXURxPXg | H5: finalizado | I5: https://youtu.be/QBfZ5DR3Htc | J5: finalizado | K5: https://youtu.be/ruv1RTn2K5c
D6: AULA 05 | E6: Teorias tradicionais do currículo: tecnicismo | F6: 0.011099537 | G6: https://youtu.be/zLNex2F2yuQ | H6: finalizado | I6: https://youtu.be/XIGS3jjz8cQ | J6: finalizado | K6: https://youtu.be/yzXgNn_pNQU
D7: AULA 06 | E7: Teorias críticas do currículo: reprodutivistas | F7: 0.014259259 | G7: https://youtu.be/JTNBzQy49pc | H7: finalizado | I7: https://youtu.be/Q8LS0u1QMDM | J7: finalizado | K7: https://youtu.be/6IWmBkGlfbQ
C8: Semana 3 | D8: AULA 07 | E8: Teorias críticas do currículo: reconceptualistas e neomarxistas | F8: 0.012847222 | G8: https://youtu.be/QLrYOm7tep0 | H8: finalizado | I8: https://youtu.be/VqP48f_MkvM | J8: finalizado | K8: https://youtu.be/hkgLaFKKLrs
D9: AULA 08 | E9: Teorias críticas do currículo: Nova Sociologia da Educação | F9: 0.0087847222 | G9: https://youtu.be/ZSiUf7cxF1M | H9: finalizado | I9: https://youtu.be/aFBm61hOKig | J9: finalizado | K9: https://youtu.be/7nFINwpLnG0
C10: Semana 4 | D10: AULA 09 | E10: Teorias críticas do currículo: pedagogia libertadora | F10: 0.011770833 | G10: https://youtu.be/Gx5MGxpz1BY | H10: finalizado | I10: https://youtu.be/QYiapV5fUVU | J10: finalizado | K10: https://youtu.be/_euO5eOBNp4
D11: AULA 10 | E11: Teorias críticas do currículo: Pedagogia dos Conteúdos | F11: 0.012071759 | G11: https://youtu.be/pz2NxQYws48 | H11: finalizado | I11: https://youtu.be/2F-0ygjwBSs | J11: finalizado | K11: https://youtu.be/evcy7Aftuu4
C12: Semana 5 | D12: AULA 11 | E12: Teorias do Currículo - Teorias pós-críticas do currículo: Multiculturalismo crítico | F12: 0.013298611 | G12: https://youtu.be/pPGT6ZWTfwU | H12: finalizado | I12: https://youtu.be/bUg25nSgmIg | J12: finalizado | K12: https://youtu.be/57mNk9uxX14
D13: AULA 12 | E13: Teorias pós-críticas do currículo: estudos feministas e teoria queer | F13: 0.01400463 | G13: https://youtu.be/o3bLXPwkKVM | H13: finalizado | I13: https://youtu.be/-oTS05zs7r8 | J13: finalizado | K13: https://youtu.be/eT1v_ywgL-w
D14: AULA 13 | E14: Teorias pós-críticas do currículo: pós-modernismo | F14: 0.0084259259 | G14: https://youtu.be/m9e9sAF1eCo | H14: finalizado | I14: https://youtu.be/WkgPavaOSB0 | J14: em correção | K14: https://youtu.be/8HAQDB_lRqE
C15: Semana 6 | D15: AULA 14 | E15: Teorias pós-críticas do currículo: pós-estruturalismo | F15: 0.012662037 | G15: https://youtu.be/NKNimSPNvb0 | H15: procedimento interno | I15: https://youtu.be/GfjUEAeh4p8 | J15: em correção | K15: https://youtu.be/h1w4vKop-oQ
D16: AULA 15 | E16: Teorias pós-críticas do currículo: pós-colonialismo | F16: 0.012534722 | G16: https://youtu.be/lh-27JpCxc4 | H16: procedimento interno | I16: https://youtu.be/zddMzhikLKk | J16: procedimento interno | K16: https://youtu.be/CzqxzN-Xh4Q
D17: AULA 16 | E17: Teorias pós-críticas do currículo: estudos culturais | F17: 0.014409722 | G17: https://youtu.be/qhXkCr70CHs | H17: finalizado | I17: https://youtu.be/HvA7y5UtEak | J17: procedimento interno | K17: https://youtu.be/t9jt6wJBmzA
D18: AULA 17 | E18: Teorias pós-críticas do currículo: princípios curriculares | F18: 0.0098148148 | G18: https://youtu.be/0LoNnmhG_GM | H18: finalizado | I18: https://youtu.be/X-TACuTZvj0 | J18: finalizado | K18: https://youtu.be/jXR1O3a6YZM
C19: Semana 7 | D19: AULA 18 | E19: Políticas curriculares | F19: 0.010625 | G19: https://youtu.be/RrXnHwuJB24 | H19: finalizado | I19: https://youtu.be/fH32emxK0lM | J19: finalizado | K19: https://youtu.be/NetNtfS3i4g
D20: AULA 19 | E20: Documentos curriculares | F20: 0.015821759 | G20: https://youtu.be/WBQdlBh6Ezo | H20: finalizado | I20: https://youtu.be/zlifHNW3djc | J20: finalizado | K20: https://youtu.be/f36WU6YJ_gw
D21: AULA 20 | E21: Projeto político-pedagógico | F21: 0.01525463 | G21: https://youtu.be/M_1gCThR1aE | H21: procedimento interno | I21: https://youtu.be/4RsrlsPngBo | J21: em edição | K21: https://youtu.be/Ucs6lY2yvcs
C22: Semana 8 | D22: AULA 21 | E22: Revisão | F22: 0.011319444 | G22: https://youtu.be/qD7xl0ZZjhk | H22: procedimento interno | I22: https://youtu.be/GS3lDKBVvNA | J22: finalizado | K22: https://youtu.be/KON6-3-XIy8
A24: COM100 | B24: Pensamento Computacional (Professor Marcos Borges) | C24: Semana 1 | D24: AULA 00 | E24: Bem-Vindos! | F24: 0.011319444 | G24: https://youtu.be/01Hb_UV-yDA | H24: finalizado | I24: https://youtu.be/AwXHHf2C2v8 | J24: finalizado
D25: AULA 01 | E25: O Século XXI e a computação na BNCC - Parte 1 | F25: 0.011319444 | G25: https://youtu.be/GGKLbcpO_DY | H25: finalizado | I25: https://youtu.be/GAl_hzwgkPQ | J25: finalizado
D26: AULA 02 | E26: O Século XXI e a computação na BNCC - Parte 2 | F26: 0.011319444 | G26: https://youtu.be/0aPzdqLQezg | H26: finalizado | I26: https://youtu.be/SeVy0by8pL4 | J26: finalizado
D27: MATERIAL DE APOIO | E27: Jovem Engenheiro | F27: 0.011319444 | G27: https://youtu.be/CavGI3hojDs | H27: finalizado | I27: https://youtu.be/zWwAzzonOgE | J27: finalizado
C28: Semana 2 | D28: AULA 03 | E28: Pensamento Computacional - Parte 1 | F28: 0.011319444 | G28: https://youtu.be/L-rQmj3xMkI | H28: finalizado | I28: https://youtu.be/faNIO2I5juk | J28: finalizado
D29: AULA 04 | E29: Pensamento Computacional - Parte 2 | F29: 0.011319444 | G29: https://youtu.be/SSTaJdLNTRY | H29: finalizado | I29: https://youtu.be/OS9aLEoCIyo | J29: finalizado
D30: AULA 05 | E30: Pensamento Computacional - Parte 3 | F30: 0.011319444 | G30: https://youtu.be/4Z5JhJylsic | H30: finalizado | I30: https://youtu.be/CoXqJJ0SKEo | J30: finalizado
D31: MATERIAL DE APOIO | E31: A teoria na prática | F31: 0.011319444 | G31: https://youtu.be/CM-U0bX-0kQ | H31: finalizado | J31: finalizado
C32: Semana 3 | D32: AULA 06 | E32: Introdução ao Scratch | F32: 0.011319444 | G32: https://youtu.be/3RW9zEiG6W4 | H32: finalizado | I32: https://youtu.be/ufFePKFDobo | J32: finalizado
D33: AULA 07 | E33: Meu primeiro programa | F33: 0.011319444 | G33: https://youtu.be/fIlciM63TLE | H33: finalizado | I33: https://youtu.be/etVsoXCc2sg | J33: finalizado
D34: AULA 08 | E34: Estruturas de repetição | F34: 0.011319444 | G34: https://youtu.be/AASk-CP-J88 | H34: finalizado | I34: https://youtu.be/iFFrLLgxLIs | J34: finalizado
C35: Semana 4 | D35: AULA 09 | E35: Condicionais - Parte 1 | F35: 0.011319444 | G35: https://youtu.be/Y9QwlY_GL_M | H35: finalizado | I35: https://youtu.be/FIiYxToV7eQ | J35: finalizado
D36: AULA 10 | E36: Condicionais - Parte 2 | F36: 0.011319444 | G36: https://youtu.be/McVt05VV8lo | H36: finalizado | I36: https://youtu.be/OuZ722lFVtM | J36: procedimento interno
D37: AULA 11 | E37: Sons, falas e fantasias | F37: 0.011319444 | G37: https://youtu.be/RcJoHOw7fbM | H37: finalizado | I37: https://youtu.be/gJh77hXYTXs | J37: finalizado
D38: AULA 12 | E38: Variáveis | F38: 0.011319444 | G38: https://youtu.be/Rgf9-jjrhDU | H38: finalizado | I38: https://youtu.be/-39VBlMzuRI | J38: finalizado
C39: Semana 5 | D39: AULA 13 | E39: Explorando projetos com arte e tecnologia no scratch | F39: 0.011319444 | G39: https://youtu.be/7e7RgvT5zUw | H39: procedimento interno | I39: https://youtu.be/UE99zvuvhMs | J39: finalizado
D40: AULA 14 | E40: Remixando projetos no scratch | F40: 0.011319444 | G40: https://youtu.be/yteOg2jkoV0 | H40: finalizado | I40: https://youtu.be/duYf995j98I | J40: finalizado
C41: Semana 6 | D41: AULA 15 | E41: Criando projetos autorais | F41: 0.011319444 | G41: https://youtu.be/Y8Nogbn5ksw | H41: procedimento interno | I41: https://youtu.be/OpMNdHWPn3o | J41: finalizado
D42: AULA 16 | E42: Criando projetos autorais com uso de extensão | F42: 0.011319444 | G42: https://youtu.be/7gJktl2k97s | H42: procedimento interno | I42: https://youtu.be/wz6lFJKZGak | J42: finalizado
C43: Semana 7 | D43: AULA 17 | E43: Conteúdo digital e inteligência artificial - Parte 1 | F43: 0.011319444 | G43: https://youtu.be/HLgWwXI5fWo | H43: finalizado | I43: https://youtu.be/3oE9Qs_dclk | J43: finalizado
D44: AULA 18 | E44: Conteúdo digital e inteligência artificial - Parte 2 | F44: 0.011319444 | G44: https://youtu.be/17dEbecypfE | H44: procedimento interno | I44: https://youtu.be/gdwbn0AL6gA | J44: finalizado
D45: AULA 19 | E45: Conteúdo digital e inteligência artificial - Parte 3 | F45: 0.011319444 | G45: https://youtu.be/CvSbIY4f0GU | H45: finalizado | I45: https://youtu.be/EE82_DVsf1E | J45: finalizado
D46: AULA 20 | E46: Conteúdo digital e inteligência artificial - Parte 4 | F46: 0.011319444 | G46: https://youtu.be/S5B31VYLlLA | H46: finalizado | I46: https://youtu.be/2zkbOYUTTZw | J46: finalizado
D47: AULA 21 | E47: Conteúdo digital e inteligência artificial - Parte 5 | F47: 0.011319444 | G47: https://youtu.be/YFjqnRr00GA | H47: finalizado | I47: https://youtu.be/uL3-GYu8KiI | J47: em correção
D48: AULA 22 | E48: Conteúdo digital e inteligência artificial - Parte 6 | F48: 0.011319444 | G48: https://youtu.be/GtFf8ZZYVE4 | H48: finalizado | I48: https://youtu.be/ztng7QRF0oQ | J48: em correção
D49: AULA 23 | E49: Conteúdo digital e inteligência artificial - Parte 7 | F49: 0.011319444 | G49: https://youtu.be/-f27KPLQeHs | H49: finalizado | I49: https://youtu.be/hsoBHM8FuvA | J49: em correção
A51: TTG-001 | B51: Metodologia Científica (Prof.Davi Nakano) | D51: AULA 01 | E51: Introdução | F51: 0.50902778 | G51: https://youtu.be/7uFgLMqYMj0
D52: AULA 02 | E52: Princípios da Pesquisa Científica | F52: 0.65694444 | G52: https://youtu.be/ddgIon2LEVQ
D53: AULA 03 | E53: Definindo o Problema de Pesquisa e o Planejamento do Projeto | F53: 0.81458333 | G53: https://youtu.be/qb-GWBrZ0XA
D54: AULA 04 | E54: Encontrando e Utilizando a Teoria | F54: 0.72986111 | G54: https://youtu.be/_Y6orSalq80
D55: AULA 05 | E55: Levantando Dados e Informações | F55: 0.59444444 | G55: https://youtu.be/IuRvyMKwR9w
D56: AULA 06 | E56: Interpretando Dados e Informações | F56: 0.66388889 | G56: https://youtu.be/6ieulJ6V4xQ
D57: AULA 07 | E57: Concluindo o Projeto de Pesquisa | F57: 0.63333333 | G57: https://youtu.be/ypEOLAGsqs0
